{
  "id": "mayuresha-stotram",
  "title": {
    "te": "మయూరేశ స్తోత్రం",
    "en": "Mayuresha Stotram",
    "hi": "मयूरेश स्तोत्रम्",
    "ta": "மயூரேஶ ஸ்தோத்ரம்"
  },
  "verses": {
    "te": [
"బ్రహ్మోవాచ |\nపురాణపురుషం దేవం నానాక్రీడాకరం ముదా |\nమాయావినం దుర్విభావ్యం మయూరేశం నమామ్యహమ్ || ౧ ||",

"పరాత్పరం చిదానందం నిర్వికారం హృది స్థితమ్ |\nగుణాతీతం గుణమయం మయూరేశం నమామ్యహమ్ || ౨ ||",

"సృజంతం పాలయంతం చ సంహరంతం నిజేచ్ఛయా |\nసర్వవిఘ్నహరం దేవం మయూరేశం నమామ్యహమ్ || ౩ ||",

"నానాదైత్యనిహంతారం నానారూపాణి బిభ్రతమ్ |\nనానాయుధధరం భక్త్యా మయూరేశం నమామ్యహమ్ || ౪ ||",

"ఇంద్రాదిదేవతావృందైరభిష్టుతమహర్నిశమ్ |\nసదసద్వ్యక్తమవ్యక్తం మయూరేశం నమామ్యహమ్ || ౫ ||",

"సర్వశక్తిమయం దేవం సర్వరూపధరం విభుమ్ |\nసర్వవిద్యాప్రవక్తారం మయూరేశం నమామ్యహమ్ || ౬ ||",

"పార్వతీనందనం శంభోరానందపరివర్ధనమ్ |\nభక్తానందకరం నిత్యం మయూరేశం నమామ్యహమ్ || ౭ ||",

"మునిధ్యేయం మునినుతం మునికామప్రపూరకమ్ |\nసమష్టివ్యష్టిరూపం త్వాం మయూరేశం నమామ్యహమ్ || ౮ ||",

"సర్వాజ్ఞాననిహంతారం సర్వజ్ఞానకరం శుచిమ్ |\nసత్యజ్ఞానమయం సత్యం మయూరేశం నమామ్యహమ్ || ౯ ||",

"అనేకకోటిబ్రహ్మాండనాయకం జగదీశ్వరమ్ |\nఅనంతవిభవం విష్ణుం మయూరేశం నమామ్యహమ్ || ౧౦ ||",

"మయూరేశ ఉవాచ |\nఇదం బ్రహ్మకరం స్తోత్రం సర్వపాపప్రనాశనమ్ |\nసర్వకామప్రదం నౄణాం సర్వోపద్రవనాశనమ్ || ౧౧ ||",

"కారాగృహగతానాం చ మోచనం దినసప్తకాత్ |\nఆధివ్యాధిహరం చైవ భుక్తిముక్తిప్రదం శుభమ్ || ౧౨ ||",

"ఇతి మయూరేశ స్తోత్రమ్ ||"
],
    "en": [
"brahmōvāca |\npurāṇapuruṣaṁ dēvaṁ nānākrīḍākaraṁ mudā |\nmāyāvinaṁ durvibhāvyaṁ mayūrēśaṁ namāmyaham || 1 ||",

"parātparaṁ cidānandaṁ nirvikāraṁ hr̥di sthitam |\nguṇātītaṁ guṇamayaṁ mayūrēśaṁ namāmyaham || 2 ||",

"sr̥jantaṁ pālayantaṁ ca saṁharantaṁ nijēcchayā |\nsarvavighnaharaṁ dēvaṁ mayūrēśaṁ namāmyaham || 3 ||",

"nānādaityanihantāraṁ nānārūpāṇi bibhratam |\nnānāyudhadharaṁ bhaktyā mayūrēśaṁ namāmyaham || 4 ||",

"indrādidēvatāvr̥ndairabhiṣṭutamaharniśam |\nsadasadvyaktamavyaktaṁ mayūrēśaṁ namāmyaham || 5 ||",

"sarvaśaktimayaṁ dēvaṁ sarvarūpadharaṁ vibhum |\nsarvavidyāpravaktāraṁ mayūrēśaṁ namāmyaham || 6 ||",

"pārvatīnandanaṁ śambhōrānandaparivardhanam |\nbhaktānandakaraṁ nityaṁ mayūrēśaṁ namāmyaham || 7 ||",

"munidhyēyaṁ muninutaṁ munikāmaprapūrakam |\nsamaṣṭivyaṣṭirūpaṁ tvāṁ mayūrēśaṁ namāmyaham || 8 ||",

"sarvājñānanihantāraṁ sarvajñānakaraṁ śucim |\nsatyajñānamayaṁ satyaṁ mayūrēśaṁ namāmyaham || 9 ||",

"anēkakōṭibrahmāṇḍanāyakaṁ jagadīśvaram |\nanantavibhavaṁ viṣṇuṁ mayūrēśaṁ namāmyaham || 10 ||",

"mayūrēśa uvāca |\nidaṁ brahmakaraṁ stōtraṁ sarvapāpapranāśanam |\nsarvakāmapradaṁ nr̥̄ṇāṁ sarvōpadravanāśanam || 11 ||",

"kārāgr̥hagatānāṁ ca mōcanaṁ dinasaptakāt |\nādhivyādhiharaṁ caiva bhuktimuktipradaṁ śubham || 12 ||",

"iti mayūrēśa stōtram ||"
],
    "hi": [
"ब्रह्मोवाच ।\nपुराणपुरुषं देवं नानाक्रीडाकरं मुदा ।\nमायाविनं दुर्विभाव्यं मयूरेशं नमाम्यहम् ॥ १ ॥",

"परात्परं चिदानन्दं निर्विकारं हृदि स्थितम् ।\nगुणातीतं गुणमयं मयूरेशं नमाम्यहम् ॥ २ ॥",

"सृजन्तं पालयन्तं च संहरन्तं निजेच्छया ।\nसर्वविघ्नहरं देवं मयूरेशं नमाम्यहम् ॥ ३ ॥",

"नानादैत्यनिहन्तारं नानारूपाणि बिभ्रतम् ।\nनानायुधधरं भक्त्या मयूरेशं नमाम्यहम् ॥ ४ ॥",

"इन्द्रादिदेवतावृन्दैरभिष्टुतमहर्निशम् ।\nसदसद्व्यक्तमव्यक्तं मयूरेशं नमाम्यहम् ॥ ५ ॥",

"सर्वशक्तिमयं देवं सर्वरूपधरं विभुम् ।\nसर्वविद्याप्रवक्तारं मयूरेशं नमाम्यहम् ॥ ६ ॥",

"पार्वतीनन्दनं शम्भोरानन्दपरिवर्धनम् ।\nभक्तानन्दकरं नित्यं मयूरेशं नमाम्यहम् ॥ ७ ॥",

"मुनिध्येयं मुनिनुतं मुनिकामप्रपूरकम् ।\nसमष्टिव्यष्टिरूपं त्वां मयूरेशं नमाम्यहम् ॥ ८ ॥",

"सर्वाज्ञाननिहन्तारं सर्वज्ञानकरं शुचिम् ।\nसत्यज्ञानमयं सत्यं मयूरेशं नमाम्यहम् ॥ ९ ॥",

"अनेककोटिब्रह्माण्डनायकं जगदीश्वरम् ।\nअनन्तविभवं विष्णुं मयूरेशं नमाम्यहम् ॥ १० ॥",

"मयूरेश उवाच ।\nइदं ब्रह्मकरं स्तोत्रं सर्वपापप्रनाशनम् ।\nसर्वकामप्रदं नॄणां सर्वोपद्रवनाशनम् ॥ ११ ॥",

"कारागृहगतानां च मोचनं दिनसप्तकात् ।\nआधिव्याधिहरं चैव भुक्तिमुक्तिप्रदं शुभम् ॥ १२ ॥",

"इति मयूरेश स्तोत्रम् ।"
],
    "ta": [
"ப்³ரஹ்மோவாச ।\nபுராணபுருஷம் தே³வம் நாநாக்ரீடா³கரம் முதா³ ।\nமாயாவிநம் து³ர்விபா⁴வ்யம் மயூரேஶம் நமாம்யஹம் ॥ 1 ॥",

"பராத்பரம் சிதா³நந்த³ம் நிர்விகாரம் ஹ்ருதி³ ஸ்தி²தம் ।\nகு³ணாதீதம் கு³ணமயம் மயூரேஶம் நமாம்யஹம் ॥ 2 ॥",

"ஸ்ருஜந்தம் பாலயந்தம் ச ஸம்ஹரந்தம் நிஜேச்ச²யா ।\nஸர்வவிக்⁴நஹரம் தே³வம் மயூரேஶம் நமாம்யஹம் ॥ 3 ॥",

"நாநாதை³த்யநிஹந்தாரம் நாநாரூபாணி பி³ப்⁴ரதம் ।\nநாநாயுத⁴த⁴ரம் ப⁴க்த்யா மயூரேஶம் நமாம்யஹம் ॥ 4 ॥",

"இந்த்³ராதி³தே³வதாவ்ருந்தை³ரபி⁴ஷ்டுதமஹர்நிஶம் ।\nஸத³ஸத்³வ்யக்தமவ்யக்தம் மயூரேஶம் நமாம்யஹம் ॥ 5 ॥",

"ஸர்வஶக்திமயம் தே³வம் ஸர்வரூபத⁴ரம் விபு⁴ம் ।\nஸர்வவித்³யாப்ரவக்தாரம் மயூரேஶம் நமாம்யஹம் ॥ 6 ॥",

"பார்வதீநந்த³நம் ஶம்போ⁴ராநந்த³பரிவர்த⁴நம் ।\nப⁴க்தாநந்த³கரம் நித்யம் மயூரேஶம் நமாம்யஹம் ॥ 7 ॥",

"முநித்⁴யேயம் முநிநுதம் முநிகாமப்ரபூரகம் ।\nஸமஷ்டிவ்யஷ்டிரூபம் த்வாம் மயூரேஶம் நமாம்யஹம் ॥ 8 ॥",

"ஸர்வாஜ்ஞாநநிஹந்தாரம் ஸர்வஜ்ஞாநகரம் ஶுசிம் ।\nஸத்யஜ்ஞாநமயம் ஸத்யம் மயூரேஶம் நமாம்யஹம் ॥ 9 ॥",

"அநேககோடிப்³ரஹ்மாண்ட³நாயகம் ஜக³தீ³ஶ்வரம் ।\nஅநந்தவிப⁴வம் விஷ்ணும் மயூரேஶம் நமாம்யஹம் ॥ 10 ॥",

"மயூரேஶ உவாச ।\nஇத³ம் ப்³ரஹ்மகரம் ஸ்தோத்ரம் ஸர்வபாபப்ரநாஶநம் ।\nஸர்வகாமப்ரத³ம் ந்ரூணாம் ஸர்வோபத்³ரவநாஶநம் ॥ 11 ॥",

"காராக்³ருஹக³தாநாம் ச மோசநம் தி³நஸப்தகாத் ।\nஆதி⁴வ்யாதி⁴ஹரம் சைவ பு⁴க்திமுக்திப்ரத³ம் ஶுப⁴ம் ॥ 12 ॥",

"இதி மயூரேஶ ஸ்தோத்ரம் ।"
]
  },
  "mangalam": {
    "te": "మంగళం మహత్",
    "en": "Maṅgalaṃ Mahat",
    "hi": "मंगलं महत्",
    "ta": "மங்களம் மஹத்"
  }
}
