{
  "id": "sri-shanmukha-shatkam",
  "title": {
    "te": "శ్రీ షణ్ముఖ షట్కం",
    "en": "Sri Shanmukha Shatkam",
    "hi": "श्री षण्मुख षट्कम्",
    "ta": "ஶ்ரீ ஷண்முக² ஷட்கம்"
  },
  "verses": {
    "te": [
  "గిరితనయాసుత గాంగపయోదిత గంధసువాసిత బాలతనో\nగుణగణభూషణ కోమలభాషణ క్రౌంచవిదారణ కుందతనో |\nగజముఖసోదర దుర్జయదానవసంఘవినాశక దివ్యతనో\nజయ జయ హే గుహ షణ్ముఖ సుందర దేహి రతిం తవ పాదయుగే || ౧ ||",
  "గిరితనయ (పార్వతి) పుత్రుడా! గంగా జలమున ఉద్భవించినవాడా! సుగంధ పరిమళములతో వాసనలు వెదజల్లే బాల్య శరీరం కలవాడా! సద్గుణములే ఆభరణములుగా కలవాడా! మృదువైన మాటలు పలికేవాడా! క్రౌంచ పర్వతాన్ని భేదించినవాడా! మొల్లపువ్వు వలె తెల్లనైన (నిర్మలమైన) దేహం కలవాడా! గజముఖుని (వినాయకుని) సోదరుడా! గెలవడానికి సాధ్యపడని రాక్షస సమూహాలను నాశనం చేసే దివ్య దేహము కలవాడా! ఓ గుహా! షణ్ముఖా! సుందరా! నీకు జయము జయము. నీ పాదద్వంద్వము నందు నాకు భక్తిని (అనురాగమును) ప్రసాదించుము.",
  "ప్రతిగిరిసంస్థిత భక్తహృదిస్థిత పుత్రధనప్రద రమ్యతనో\nభవభయమోచక భాగ్యవిధాయక భూసుతవార సుపూజ్యతనో |\nబహుభుజశోభిత బంధవిమోచక బోధఫలప్రద బోధతనో\nజయ జయ హే గుహ షణ్ముఖ సుందర దేహి రతిం తవ పాదయుగే || ౨ ||",
  "ప్రతి పర్వతముపై కొలువై ఉన్నవాడా! భక్తుల హృదయములలో నివసించేవాడా! పుత్రులను, ధనమును ప్రసాదించే రమ్యమైన రూపం కలవాడా! సంసార భయము నుండి విముక్తి కలిగించేవాడా! భాగ్యములను కూర్చేవాడా! భూసుత (మంగళ గ్రహం/కుజుడు) వారమున విశేషంగా పూజించబడే శరీరం కలవాడా! అనేక బాహువులతో శోభించేవాడా! బంధనాల నుండి విడిపించేవాడా! జ్ఞానమనే ఫలాన్ని ఇచ్చే జ్ఞాన స్వరూపుడా! ఓ గుహా! షణ్ముఖా! సుందరా! నీకు జయము జయము. నీ పాదద్వంద్వము నందు నాకు భక్తిని ప్రసాదించుము.",
  "శమధనమానిత మౌనిహృదాలయ మోక్షకృదాలయ ముగ్ధతనో\nశతమఖపాలక శంకరతోషక శంఖసువాదక శక్తితనో |\nదశశతమన్మథ సన్నిభసుందర కుండలమండిత కర్ణవిభో\nజయ జయ హే గుహ షణ్ముఖ సుందర దేహి రతిం తవ పాదయుగే || ౩ ||",
  "శాంతమే ధనముగా కలిగిన మునుల హృదయాలయములలో ఉండేవారు మెచ్చుకునేవాడా! మోక్షాన్ని ప్రసాదించే ఆలయము వంటివాడా! మనోహరమైన (ముగ్ధ) రూపం కలవాడా! ఇంద్రుని (శతమఖుని) పాలించేవాడా! శంకరునికి సంతోషాన్ని కలిగించేవాడా! శంఖము వంటి చక్కని కంఠధ్వని కలవాడా! శక్తి ఆయుధాన్ని ధరించినవాడా! వేయిమంది మన్మథులతో సమానమైన సౌందర్యము కలవాడా! కుండలములతో అలంకరించబడిన కర్ణములు (చెవులు) కలిగిన ప్రభువా! ఓ గుహా! షణ్ముఖా! సుందరా! నీకు జయము జయము. నీ పాదద్వంద్వము నందు నాకు భక్తిని ప్రసాదించుము.",
  "గుహ తరుణారుణచేలపరిష్కృత తారకమారక మారతనో\nజలనిధితీరసుశోభివరాలయ శంకరసన్నుత దేవగురо |\nవిహితమహాధ్వరసామనిమంత్రిత సౌమ్యహృదంతర సోమతనో\nజయ జయ హే గుహ షణ్ముఖ సుందర దేహి రతిం తవ పాదయుగే || ౪ ||",
  "ఓ గుహుడా! బాల సూర్యుని వలె ఎర్రనైన వస్త్రములతో అలంకరించబడినవాడా! తారకాసురుని సంహరించినవాడా! మన్మథుని వంటి శరీర సౌందర్యము కలవాడా! సముద్ర తీరమున (తిరుచెందూర్ వంటి క్షేత్రాలలో) శోభించే శ్రేష్ఠమైన ఆలయము కలవాడా! శంకరునిచేతనే స్తుతించబడిన దేవగురువైనవాడా! శాస్త్రోక్తమైన మహా యజ్ఞములలో సామవేద మంత్రములచే ఆహ్వానించబడేవాడా! సౌమ్యులైన భక్తుల హృదయములలో చంద్రుని వంటి ఆహ్లాదకరమైన రూపము కలవాడా! ఓ షణ్ముఖా! సుందరా! నీకు జయము జయము. నీ పాదద్వంద్వము నందు నాకు భక్తిని ప్రసాదించుము.",
  "లవలికయా సహ కేలికలాపర దేవసుతార్పిత మాల్యతనో\nగురుపదసంస్థిత శంకరదర్శిత తత్త్వమయప్రణవార్థవిభో |\nవిధిహరిపూజిత బ్రహ్మసుతార్పిత భాగ్యసుపూరక యోగితనో\nజయ జయ హే గుహ షణ్ముఖ సుందర దేహి రతిం తవ పాదయుగే || ౫ ||",
  "వల్లీ దేవి (లవలిక) తో కలిసి క్రీడలందు ఆసక్తి కలవాడా! దేవకన్యలచే సమర్పించబడిన పూలమాలలు ధరించిన శరీరం కలవాడా! గురు పీఠముపై ఆసీనుడవై శంకరునకు (తండ్రికి) తత్త్వముతో కూడిన ప్రణవ మంత్రము యొక్క అర్థమును బోధించిన ప్రభువా! బ్రహ్మ విష్ణువులచే పూజించబడినవాడా! సరస్వతీ దేవి (బ్రహ్మసుత) చేత ఆరాధించబడినవాడా! భాగ్యములను నిండుగా ఇచ్చే యోగమూర్తివి! ఓ షణ్ముఖా! సుందరా! నీకు జయము జయము. నీ పాదద్వంద్వము నందు నాకు భక్తిని ప్రసాదించుము.",
  "కలిజనపాలన కంజసులోచన కుక్కుటకేతన కేలితనో\nకృతబలిపాలన బర్హిణవాహన ఫాలవిలోచనశంభుతనో |\nశరవణసంభవ శత్రునిబర్హణ చంద్రసమానన శర్మతనో\nజయ జయ హే గుహ షణ్ముఖ సుందర దేహి రతిం తవ పాదయుగే || ౬ ||",
  "కలియుగ జనులను పాలించేవాడా! తామర రేకుల వంటి చక్కని కన్నులు కలవాడా! కోడి పుంజు ధ్వజముగా కలవాడా! లీలా వినోదములే దేహముగా కలవాడా! భక్తులు చేసే పూజలను స్వీకరించి పాలించేవాడా! నెమలి వాహనము కలవాడా! ఫాలాక్షుడైన శంభుని అంశతో జన్మించిన దేహము కలవాడా! శరవణ భవమున (నాములలో) ఉద్భవించినవాడా! శత్రువులను అణచివేసేవాడా! చంద్రబింబము వంటి ముఖము కలవాడా! ఆనందమయమైన రూపము కలవాడా! ఓ షణ్ముఖా! సుందరా! నీకు జయము జయము. నీ పాదద్వంద్వము నందు నాకు భక్తిని ప్రసాదించుము.",
  "సుఖదమనంతపదాన్విత రామసుదీక్షిత సత్కవిపద్యమిదం\nశరవణ సంభవ తోషదమిష్టదమష్టసుసిద్ధిదమార్తిహరమ్ |\nపఠతి శృణోతి చ భక్తియుతో యది భాగ్యసమృద్ధిమథో లభతే\nజయ జయ హే గుహ షణ్ముఖ సుందర దేహి రతిం తవ పాదయుగే || ౭ ||",
  "సుఖాన్ని ఇచ్చేది, అనంతమైన పదములతో కూడినది, అనంతరామ దీక్షితులనే సత్కవిచే రచింపబడిన ఈ పద్య మాలిక… శరవణభవునికి సంతోషాన్ని కలిగిస్తుంది, కోరిన కోర్కెలు తీరుస్తుంది, అష్టసిద్ధులను ప్రసాదిస్తుంది మరియు దుఃఖాలను హరిస్తుంది. ఎవడైతే భక్తితో దీనిని పఠిస్తాడో లేదా వింటాడో, అతడు భాగ్య సమృద్ధిని పొందుతాడు. ఓ షణ్ముఖా! సుందరా! నీకు జయము జయము. నీ పాదద్వంద్వము నందు నాకు భక్తిని ప్రసాదించుము.",
  "ఇతి శ్రీఅనంతరామదీక్షిత కృతం షణ్ముఖ షట్కమ్ ||"
],
    "en": [
  "giritanayāsuta gāṅgapayōdita gandhasuvāsita bālatanō\nguṇagaṇabhūṣaṇa kōmalabhāṣaṇa krauñcavidāraṇa kundatanō |\ngajamukhasōdara durjayadānavasaṅghavināśaka divyatanō\njaya jaya hē guha ṣaṇmukha sundara dēhi ratiṁ tava pādayugē || 1 ||",
  "pratigirisaṁsthita bhaktahr̥disthita putradhanaprada ramyatanō\nbhavabhayamōcaka bhāgyavidhāyaka bhūsutavāra supūjyatanō |\nbahubhujaśōbhita bandhavimōcaka bōdhaphalaprada bōdhatanō\njaya jaya hē guha ṣaṇmukha sundara dēhi ratiṁ tava pādayugē || 2 ||",
  "śamadhanamānita maunihr̥dālaya mōkṣakr̥dālaya mugdhatanō\nśatamakhapālaka śaṅkaratōṣaka śaṅkhasuvādaka śaktitanō |\ndaśaśatamanmatha sannibhasundara kuṇḍalamaṇḍita karṇavibhō\njaya jaya hē guha ṣaṇmukha sundara dēhi ratiṁ tava pādayugē || 3 ||",
  "guha taruṇāruṇacēlapariṣkr̥ta tārakamāraka māratanō\njalanidhitīrasuśōbhivarālaya śaṅkarasannuta dēvagurō |\nvihitamahādhvarasāmanimantrita saumyahr̥dantara sōmatanō\njaya jaya hē guha ṣaṇmukha sundara dēhi ratiṁ tava pādayugē || 4 ||",
  "lavalikayā saha kēlikalāpara dēvasutārpita mālyatanō\ngurupadasaṁsthita śaṅkaradarśita tattvamayapraṇavārthavibhō |\nvidhiharipūjita brahmasutārpita bhāgyasupūraka yōgitanō\njaya jaya hē guha ṣaṇmukha sundara dēhi ratiṁ tava pādayugē || 5 ||",
  "kalijanapālana kañjasulōcana kukkuṭakētana kēlitanō\nkr̥tabalipālana barhiṇavāhana phālavilōcanaśambhutanō |\nśaravaṇasambhava śatrunibarhaṇa candrasamānana śarmatanō\njaya jaya hē guha ṣaṇmukha sundara dēhi ratiṁ tava pādayugē || 6 ||",
  "sukhadamanantapadānvita rāmasudīkṣita satkavipadyamidaṁ\nśaravaṇa sambhava tōṣadamiṣṭadamaṣṭasusiddhidamārtiharam |\npaṭhati śr̥ṇōti ca bhaktiyutō yadi bhāgyasamr̥ddhimathō labhatē\njaya jaya hē guha ṣaṇmukha sundara dēhi ratiṁ tava pādayugē || 7 ||",
  "iti śrīanantarāmadīkṣita kr̥taṁ ṣaṇmukha ṣaṭkam ||"
],
    "hi": [
  "गिरितनयासुत गाङ्गपयोदित गन्धसुवासित बालतनो\nगुणगणभूषण कोमलभाषण क्रौञ्चविदारण कुन्दतनो ।\nगजमुखसोदर दुर्जयदानवसङ्घविनाशक दिव्यतनो\nजय जय हे गुह षण्मुख सुन्दर देहि रतिं तव पादयुगे ॥ १ ॥",
  "प्रतिगिरिसंस्थित भक्तहृदिस्थित पुत्रधनप्रद रम्यतनो\nभवभयमोचक भाग्यविधायक भूसुतवार सुपूज्यतनो ।\nबहुभुजशोभित बन्धविमोचक बोधफलप्रद बोधतनो\nजय जय हे गुह षण्मुख सुन्दर देहि रतिं तव पादयुगे ॥ २ ॥",
  "शमधनमानित मौनिहृदालय मोक्षकृदालय मुग्धतनो\nशतमखपालक शङ्करतोषक शङ्खसुवादक शक्तितनो ।\nदशशतमन्मथ सन्निभसुन्दर कुण्डलमण्डित कर्णविभो\nजय जय हे गुह षण्मुख सुन्दर देहि रतिं तव पादयुगे ॥ ३ ॥",
  "गुह तरुणारुणचेलपरिष्कृत तारकमारक मारतनो\nजलनिधितीरसुशोभिवरालय शङ्करसन्नुत देवगुरो ।\nविहितमहाध्वरसामनिमन्त्रित सौम्यहृदन्तर सोमतनो\nजय जय हे गुह षण्मुख सुन्दर देहि रतिं तव पादयुगे ॥ ४ ॥",
  "लवलिकया सह केलिकलापर देवसुतार्पित माल्यतनो\nगुरुपदसंस्थित शङ्करदर्शित तत्त्वमयप्रणवार्थविभो ।\nविधिहरिपूजित ब्रह्मसुतार्पित भाग्यसुपूरक योगितनो\nजय जय हे गुह षण्मुख सुन्दर देहि रतिं तव पादयुगे ॥ ५ ॥",
  "कलिजनपालन कञ्जसुलोचन कुक्कुटकेतन केलितनो\nकृतबलिपालन बर्हिणवाहन फालविलोचनशम्भुतनो ।\nशरवणसम्भव शत्रुनिबर्हण चन्द्रसमानन शर्मतनो\nजय जय हे गुह षण्मुख सुन्दर देहि रतिं तव पादयुगे ॥ ६ ॥",
  "सुखदमनन्तपदान्वित रामसुदीक्षित सत्कविपद्यमिदं\nशरवण सम्भव तोषदमिष्टदमष्टसुसिद्धिदमार्तिहरम् ।\nपठति शृणोति च भक्तियुतो यदि भाग्यसमृद्धिमथो लभते\nजय जय हे गुह षण्मुख सुन्दर देहि रतिं तव पादयुगे ॥ ७ ॥",
  "इति श्रीअनन्तरामदीक्षित कृतं षण्मुख षट्कम् ॥"
],
    "ta": [
  "கி³ரிதநயாஸுத கா³ங்க³பயோதி³த க³ந்த⁴ஸுவாஸித பா³லதநோ\nகு³ணக³ணபூ⁴ஷண கோமளபா⁴ஷண க்ரௌஞ்சவிதா³ரண குந்த³தநோ ।\nக³ஜமுக²ஸோத³ர து³ர்ஜயதா³நவஸங்க⁴விநாஶக தி³வ்யதநோ\nஜய ஜய ஹே கு³ஹ ஷண்முக² ஸுந்த³ர தே³ஹி ரதிம் தவ பாத³யுகே³ ॥ 1 ॥",
  "ப்ரதிகி³ரிஸம்ஸ்தி²த ப⁴க்தஹ்ருதி³ஸ்தி²த புத்ரத⁴நப்ரத³ ரம்யதநோ\nப⁴வப⁴யமோசக பா⁴க்³யவிதா⁴யக பூ⁴ஸுதவார ஸுபூஜ்யதநோ ।\nப³ஹுபு⁴ஜஶோபி⁴த ப³ந்த⁴விமோசக போ³த⁴ப²லப்ரத³ போ³த⁴தநோ\nஜய ஜய ஹே கு³ஹ ஷண்முக² ஸுந்த³ர தே³ஹி ரதிம் தவ பாத³யுகே³ ॥ 2 ॥",
  "ஶமத⁴நமாநித மௌநிஹ்ருதா³ளய மோக்ஷக்ருதா³ளய முக்³த⁴தநோ\nஶதமக²பாலக ஶங்கரதோஷக ஶங்க²ஸுவாத³க ஶக்திதநோ ।\nத³ஶஶதமந்மத² ஸந்நிப⁴ஸுந்த³ர குண்ட³லமண்டி³த கர்ணவிபோ⁴\nஜய ஜய ஹே கு³ஹ ஷண்முக² ஸுந்த³ர தே³ஹி ரதிம் தவ பாத³யுகே³ ॥ 3 ॥",
  "கு³ஹ தருணாருணசேலபரிஷ்க்ருத தாரகமாரக மாரதநோ\nஜலநிதி⁴தீரஸுஶோபி⁴வராளய ஶங்கரஸந்நுத தே³வகு³ரோ ।\nவிஹிதமஹாத்⁴வரஸாமநிமந்த்ரித ஸௌம்யஹ்ருத³ந்தர ஸோமதநோ\nஜய ஜய ஹே கு³ஹ ஷண்முக² ஸுந்த³ர தே³ஹி ரதிம் தவ பாத³யுகே³ ॥ 4 ॥",
  "லவலிகயா ஸஹ கேலிகலாபர தே³வஸுதார்பித மால்யதநோ\nகு³ருபத³ஸம்ஸ்தி²த ஶங்கரத³ர்ஶித தத்த்வமயப்ரணவார்த²விபோ⁴ ।\nவிதி⁴ஹரிபூஜித ப்³ரஹ்மஸுதார்பித பா⁴க்³யஸுபூரக யோகி³தநோ\nஜய ஜய ஹே கு³ஹ ஷண்முக² ஸுந்த³ர தே³ஹி ரதிம் தவ பாத³யுகே³ ॥ 5 ॥",
  "கலிஜநபாலந கஞ்ஜஸுலோசந குக்குடகேதந கேலிதநோ\nக்ருதப³லிபாலந ப³ர்ஹிணவாஹந பா²லவிளோசநஶம்பு⁴தநோ ।\nஶரவணஸம்ப⁴வ ஶத்ருநிப³ர்ஹண சந்த்³ரஸமாநந ஶர்மதநோ\nஜய ஜய ஹே கு³ஹ ஷண்முக² ஸுந்த³ர தே³ஹி ரதிம் தவ பாத³யுகே³ ॥ 6 ॥",
  "ஸுக²த³மநந்தபதா³ந்வித ராமஸுதீ³க்ஷித ஸத்கவிபத்³யமித³ம்\nஶரவண ஸம்ப⁴வ தோஷத³மிஷ்டத³மஷ்டஸுஸித்³தி⁴த³மார்திஹரம் ।\nபட²தி ஶ்ருணோதி ச ப⁴க்தியுதோ யதி³ பா⁴க்³யஸம்ருத்³தி⁴மதோ² லப⁴தே\nஜய ஜய ஹே கு³ஹ ஷண்முக² ஸுந்த³ர தே³ஹி ரதிம் தவ பாத³யுகே³ ॥ 7 ॥",
  "இதி ஶ்ரீஅநந்தராமதீ³க்ஷித க்ருதம் ஷண்முக² ஷட்கம் ॥"
]
  },
  "mangalam": {
    "te": "మంగళం మహత్",
    "en": "Maṅgalaṃ Mahat",
    "hi": "मंगलं महत्",
    "ta": "மங்களம் மஹத்"
  }
}
