{
  "id": "ashtadasha-shaktipeetha-stotram",
  "title": {
    "te": "అష్టాదశ శక్తిపీఠ స్తోత్రం",
    "en": "Ashtadasa Shakthi Peetha Stotram",
    "hi": "अष्टादशशक्तिपीठ स्तोत्रम्",
    "ta": "அஷ்டாத³ஶ ஶக்திபீட² ஸ்தோத்ரம்"
  },
  "verses": {
    "te": [
  "లంకాయాం శాంకరీదేవీ కామాక్షీ కాంచికాపురే |\n",
  "ప్రద్యుమ్నే శృంఖళాదేవీ చాముండీ క్రౌంచపట్టణే || ౧ ||\n",
  "\n",
  "అలంపురే జోగులాంబా శ్రీశైలే భ్రమరాంబికా |\n",
  "కొల్హాపురే మహాలక్ష్మీ ముహుర్యే ఏకవీరికా || ౨ ||\n",
  "\n",
  "ఉజ్జయిన్యాం మహాకాళీ పీఠిక్యాం పురుహూతికా |\n",
  "ఓఢ్యాయాం గిరిజాదేవీ మాణిక్యా దక్షవాటకే || ౩ ||\n",
  "\n",
  "హరిక్షేత్రే కామరూపా ప్రయాగే మాధవేశ్వరీ |\n",
  "జ్వాలాయాం వైష్ణవీదేవీ గయా మాంగళ్యగౌరికా || ౪ ||\n",
  "\n",
  "వారాణస్యాం విశాలాక్షీ కాశ్మీరేషు సరస్వతీ |\n",
  "అష్టాదశ సుపీఠాని యోగినామపి దుర్లభమ్ || ౫ ||\n",
  "\n",
  "సాయంకాలే పఠేన్నిత్యం సర్వశత్రువినాశనమ్ |\n",
  "సర్వరోగహరం దివ్యం సర్వసంపత్కరం శుభమ్ || ౬ ||\n",
  "\n",
  "ఇతి అష్టాదశ శక్తిపీఠ స్తోత్రమ్ |\n"
],
    "en": [
  "laṅkāyāṁ śāṅkarīdēvī kāmākṣī kāñcikāpurē |\n",
  "pradyumnē śr̥ṅkhalādēvī cāmuṇḍī krauñcapaṭ-ṭaṇē || 1 ||\n",
  "\n",
  "alampurē jōgulāmbā śrīśailē bhramarāmbikā |\n",
  "kōlhāpurē mahālakṣmī muhuryē ēkavīrikā || 2 || [māhuryē]\n",
  "\n",
  "ujjayinyāṁ mahākālī pīṭhikyāṁ puruhūtikā |\n",
  "ōḍhyāyāṁ girijādēvī māṇikyā dakṣavāṭakē || 3 ||\n",
  "\n",
  "harikṣētrē kāmarūpā prayāgē mādhavēśvarī |\n",
  "jvālāyāṁ vaiṣṇavīdēvī gayā māṅgalyagaurikā || 4 ||\n",
  "\n",
  "vārāṇasyāṁ viśālākṣī kāśmīrēṣu sarasvatī |\n",
  "aṣṭādaśa supīṭhāni yōgināmapi durlabham || 5 ||\n",
  "\n",
  "sāyaṅkālē paṭhēnnityaṁ sarvaśatruvināśanam |\n",
  "sarvarōgaharaṁ divyaṁ sarvasampatkaraṁ śubham || 6 ||\n",
  "\n",
  "iti aṣṭādaśa śaktipīṭha stōtram |\n"
],
    "hi": [
  "लङ्कायां शाङ्करीदेवी कामाक्षी काञ्चिकापुरे ।\n",
  "प्रद्युम्ने शृङ्खलादेवी चामुण्डी क्रौञ्चपट्‍टणे ॥ १ ॥\n",
  "\n",
  "अलम्पुरे जोगुलाम्बा श्रीशैले भ्रमराम्बिका ।\n",
  "कोल्हापुरे महालक्ष्मी मुहुर्ये एकवीरिका ॥ २ ॥\n",
  "\n",
  "उज्जयिन्यां महाकाली पीठिक्यां पुरुहूतिका ।\n",
  "ओढ्यायां गिरिजादेवी माणिक्या दक्षवाटके ॥ ३ ॥\n",
  "\n",
  "हरिक्षेत्रे कामरूपा प्रयागे माधवेश्वरी ।\n",
  "ज्वालायां वैष्णवीदेवी गया माङ्गल्यगौरिका ॥ ४ ॥\n",
  "\n",
  "वाराणस्यां विशालाक्षी काश्मीरेषु सरस्वती ।\n",
  "अष्टादश सुपीठानि योगिनामपि दुर्लभम् ॥ ५ ॥\n",
  "\n",
  "सायङ्काले पठेन्नित्यं सर्वशत्रुविनाशनम् ।\n",
  "सर्वरोगहरं दिव्यं सर्वसम्पत्करं शुभम् ॥ ६ ॥\n",
  "\n",
  "इति अष्टादश शक्तिपीठ स्तोत्रम् ।\n"
],
    "ta": [
  "லங்காயாம் ஶாங்கரீதே³வீ காமாக்ஷீ காஞ்சிகாபுரே ।\n",
  "ப்ரத்³யும்நே ஶ்ருங்க²லாதே³வீ சாமுண்டீ³ க்ரௌஞ்சபட்டணே ॥ 1 ॥\n",
  "\n",
  "அலம்புரே ஜோகு³ளாம்பா³ ஶ்ரீஶைலே ப்⁴ரமராம்பி³கா ।\n",
  "கோல்ஹாபுரே மஹாலக்ஷ்மீ முஹுர்யே ஏகவீரிகா ॥ 2 ॥ [மாஹுர்யே]\n",
  "\n",
  "உஜ்ஜயிந்யாம் மஹாகாளீ பீடி²க்யாம் புருஹூதிகா ।\n",
  "ஓட்⁴யாயாம் கி³ரிஜாதே³வீ மாணிக்யா த³க்ஷவாடகே ॥ 3 ॥\n",
  "\n",
  "ஹரிக்ஷேத்ரே காமரூபா ப்ரயாகே³ மாத⁴வேஶ்வரீ ।\n",
  "ஜ்வாலாயாம் வைஷ்ணவீதே³வீ க³யா மாங்க³ல்யகௌ³ரிகா ॥ 4 ॥\n",
  "\n",
  "வாராணஸ்யாம் விஶாலாக்ஷீ காஶ்மீரேஷு ஸரஸ்வதீ ।\n",
  "அஷ்டாத³ஶ ஸுபீடா²நி யோகி³நாமபி து³ர்லப⁴ம் ॥ 5 ॥\n",
  "\n",
  "ஸாயங்காலே படே²ந்நித்யம் ஸர்வஶத்ருவிநாஶநம் ।\n",
  "ஸர்வரோக³ஹரம் தி³வ்யம் ஸர்வஸம்பத்கரம் ஶுப⁴ம் ॥ 6 ॥\n",
  "\n",
  "இதி அஷ்டாத³ஶ ஶக்திபீட² ஸ்தோத்ரம் ।\n"
]
  },
  "mangalam": {
    "te": "మంగళం మహత్",
    "en": "Maṅgalaṃ Mahat",
    "hi": "मंगलं महत्",
    "ta": "மங்களம் மஹத்"
  }
}
