{
  "id": "rudra-namaka-stotram",
  "title": {
    "te": "రుద్రాధ్యాయ స్తుతిః (రుద్ర నమక స్తోత్రం)",
    "en": "Rudradhyaya Stuti (Rudra Namaka Stotram)",
    "hi": "रुद्राध्याय स्तुतिः (रुद्र नमक स्तोत्रम्)",
    "ta": "ருத்³ராத்⁴யாய ஸ்துதி꞉ (ருத்³ர நமக ஸ்தோத்ரம்)"
  },
  "verses": {
    "te": [
      "ధ్యానం –\n",
      "ఆపాతాళ నభః స్థలాంత భువన బ్రహ్మాండమావిస్ఫుర-\n",
      "-జ్జ్యోతిఃస్ఫాటికలింగ మౌళివిలసత్ పూర్ణేందు వాంతామృతైః |\n",
      "అస్తోకాప్లుతమేకమీశమనిశం రుద్రానువాకాన్ జపన్\n",
      "ధ్యాయేదీప్సితసిద్ధయే ధ్రువపదం విప్రోఽభిషించేచ్ఛివమ్ ||\n",
      "\n",
      "బ్రహ్మాండవ్యాప్తదేహా భసిత హిమరుచా భాసమానా భుజంగైః\n",
      "కంఠే కాలాః కపర్దాః కలితశశికలాశండ కోదండ హస్తాః |\n",
      "త్ర్యక్షా రుద్రాక్షమాలాః సులలితవపుషః శాంభవా మూర్తిభేదాః\n",
      "రుద్రాః శ్రీరుద్రసూక్త ప్రకటిత విభవాః నః ప్రయచ్ఛంతు సౌఖ్యమ్ ||\n",
      "\n",
      "ఇత్యుక్త్వా సత్వరం సాంబం స్మృత్వా శంకరపాదుకే |\n",
      "ధ్యాత్వా యయౌ గణాధీశః శివసన్నిధిమాదరాత్ ||\n",
      "\n",
      "తతః ప్రణమ్య బహుధా కృతాంజలిపుటః ప్రభుమ్ |\n",
      "శంభుం స్తోతుం మతిం చక్రే సర్వాభీష్టప్రదాయకమ్ ||\n",
      "\n",
      "గణేశ ఉవాచ |\n",
      "నమస్తే దేవదేవాయ నమస్తే రుద్రమన్యవే |\n",
      "నమస్తే చంద్రచూడాయాప్యుతోత ఇషవే నమః || ౧ ||\n",
      "\n",
      "నమస్తే పార్వతీకాంతాయైకరూపాయ ధన్వనే |\n",
      "నమస్తే భగవన్ శంభో బాహుభ్యాముత తే నమః || ౨ ||\n",
      "\n",
      "ఇషుః శివతమా యా తే తయా మృడాయ రుద్ర మామ్ |\n",
      "శివం ధనుర్యద్బభూవ తేనాపి మృడయాధునా || ౩ ||\n",
      "\n",
      "శరవ్యా యా శివతమా తయాపి మృడయ ప్రభో |\n",
      "యా తే రుద్ర శివా నిత్యం సర్వమంగళసాధనమ్ || ౪ ||\n",
      "\n",
      "తయాభిచాకశీహి త్వం తనువా మాముమాపతే |\n",
      "అఘోరయాపి తనువా రుద్రాద్యాపాపకాశినీ || ౫ ||\n",
      "\n",
      "యా తయా మృడయ స్వామిన్ సదా శంతమయా ప్రభో |\n",
      "గిరిశంతం మహారుద్ర హస్తే యామిషుమస్తవే || ౬ ||\n",
      "\n",
      "బిభర్షి తాం గిరిత్రాద్య శివాం కురు శివాపతే |\n",
      "శివేన వచసా రుద్ర నిత్యం వాచా వదామసి || ౭ ||\n",
      "\n",
      "త్వద్భక్తి పరిపూతాంగం మహింసీః పురుషం జగత్ |\n",
      "యచ్చ శర్వ జగత్సర్వమయక్ష్మం సుమనా అసత్ || ౮ ||\n",
      "\n",
      "యథా తథావమాం రుద్ర తదన్యధాపి మే ప్రభో |\n",
      "రుద్ర త్వం ప్రథమో దైవ్యో భిషక్ పాపవినాశకః || ౯ ||\n",
      "\n",
      "అధివక్తాఽధ్యవోచన్మాం భావలింగార్చకం ముదా |\n",
      "అహీన్ సర్వాన్ యాతు ధాన్యః సర్వా అప్యద్య జంభయన్ || ౧౦ ||\n",
      "\n",
      "అసౌ తామ్రోరుణో బభ్రుః నీలగ్రీవః సుమంగళః |\n",
      "విలోహితోస్త్వయం శంభో త్వదధిష్ఠాన ఏవ హి || ౧౧ ||\n",
      "\n",
      "నమో నమస్తే భగవన్ నీలగ్రీవాయ మీఢుషే |\n",
      "సహస్రాక్షాయ శుద్ధాయ సచ్చిదానందమూర్తయే || ౧౨ ||\n",
      "\n",
      "ఉభయోగార్త్నియోర్జ్యా యా ధన్వనస్తాం ప్రముంచతామ్ |\n",
      "సంప్రాప్య ధనురన్యేషాం భయాయ ప్రభవిష్యతి || ౧౩ ||\n",
      "\n",
      "అస్మద్భయ వినాశార్థ మధునాభయద ప్రభో |\n",
      "యాశ్చ తే హస్త ఇషవః పరతా భగవో వాప || ౧౪ ||\n",
      "\n",
      "అవతత్య ధనుశ్చ త్వం సహస్రాక్ష శతేషుధే |\n",
      "ముఖా నిశీర్య శల్యానాం శివో నః సుమనా భవ || ౧౫ ||\n",
      "\n",
      "విజ్యం ధనురిదం భూయాత్ విశల్యో బాణవానపి |\n",
      "అనేశన్నిషవశ్చాపి హ్యాభురస్తు నిషంగథిః || ౧౬ ||\n",
      "\n",
      "కపర్దినో మహేశస్య యది నాభుర్నిషంగథిః |\n",
      "ఇషవో పి సమర్థాశ్చేత్ సామర్థ్యేతు భయం భవేత్ || ౧౭ ||\n",
      "\n",
      "యా తే హేతిర్ధనుర్హస్తే మీఢుష్టమ బభూవ యా |\n",
      "తయాఽస్మాన్ విశ్వతస్తేన పాలయ త్వమయక్ష్మయా || ౧౮ ||\n",
      "\n",
      "అనాతతాయాయుధాయ నమస్తే ధృష్ణవే నమః |\n",
      "బాహుభ్యాం ధన్వనే శంభో నమో భూయో నమో నమః || ౧౯ ||\n",
      "\n",
      "పరితే ధన్వనో హేతిః విశ్వతోఽస్మాన్ వృణక్తు నః |\n",
      "ఇషుధిస్తవ యా తావదస్మదారే నిధేహి తమ్ || ౨౦ ||\n",
      "\n",
      "హిరణ్యబాహవే తుభ్యం సేనాన్యే తే నమో నమః |\n",
      "దిశాం చ పతయే తుభ్యం పశూనాం పతయే నమః || ౨౧ ||\n",
      "\n",
      "త్విషీమతే నమస్తుభ్యం నమః సస్పింజరాయ తే |\n",
      "నమః పథీనాం పతయే బభ్లుశాయ నమో నమః || ౨౨ ||\n",
      "\n",
      "నమో వివ్యాధినేన్నానాం పతయే ప్రభవే నమః |\n",
      "నమస్తే హరికేశాయ రుద్రాయాస్తూపవీతినే || ౨౩ ||\n",
      "\n",
      "పుష్టానాం పతయే తుభ్యం జగతాం పతయే నమః |\n",
      "సంసార హేతి రూపాయ రుద్రాయాప్యాతతాయినే || ౨౪ ||\n",
      "\n",
      "క్షేత్రాణాం పతయే తుభ్యం సూతాయ సుకృతాత్మనే |\n",
      "అహంత్యాయ నమస్తుభ్యం వనానాం పతయే నమః || ౨౫ ||\n",
      "\n",
      "రోహితాయ స్థపతయే మంత్రిణే వాణిజాయ చ |\n",
      "కక్షాణాం పతయే తుభ్యం నమస్తుభ్యం భువంతయే || ౨౬ ||\n",
      "\n",
      "తద్వారివస్కృతాయాస్తు మహాదేవాయ తే నమః |\n",
      "ఓషాధీనాం చ పతయే నమస్తుభ్యం మహాత్మనే || ౨౭ ||\n",
      "\n",
      "ఉచ్చైర్ఘోషాయ ధీరాయ ధీరాన్ క్రందయతే నమః || ౨౮ ||\n",
      "\n",
      "పత్తీనాం పతయే తుభ్యం కృత్స్నవీతాయ తే నమః |\n",
      "ధావతే ధవలాయాపి సత్త్వనాం పతయే నమః || ౨౯ ||\n",
      "\n",
      "ఆవ్యాధినీనాం పతయే కకుభాయ నిషంగిణే |\n",
      "స్తేనానాం పతయే తుభ్యం దివ్యేషుధిమతే నమః || ౩౦ ||\n",
      "\n",
      "తస్కరాణాం చ పతయే వంచతే పరివంచతే |\n",
      "స్తాయూనాం పతయే తుభ్యం నమస్తేఽస్తు నిచేరవే || ౩౧ ||\n",
      "\n",
      "నమః పరిచరాయాఽపి మహారుద్రాయ తే నమః |\n",
      "అరణ్యానాం చ పతయే ముష్ణతాం పతయే నమః || ౩౨ ||\n",
      "\n",
      "ఉష్ణీషిణే నమస్తుభ్యం నమో గిరిచరాయ తే |\n",
      "కులుంచానాం చ పతయే నమస్తుభ్యం భవాయ చ || ౩౩ ||\n",
      "\n",
      "నమో రుద్రాయ శర్వాయ తుభ్యం పశుపతే నమః |\n",
      "నమ ఉగ్రాయ భీమాయ నమశ్చాగ్రేవధాయ చ || ౩౪ ||\n",
      "\n",
      "నమో దూరేవధాయాఽపి నమో హంత్రే నమో నమః |\n",
      "హనీయసే నమస్తుభ్యం నీలగ్రీవాయ తే నమః || ౩౫ ||\n",
      "\n",
      "నమస్తే శితికంఠాయ నమస్తేఽస్తు కపర్దినే |\n",
      "నమస్తే వ్యుప్తకేశాయ సహస్రాక్షాయ మీఢుషే || ౩౬ ||\n",
      "\n",
      "గిరిశాయ నమస్తేఽస్తు శిపివిష్టాయ తే నమః |\n",
      "నమస్తే శంభవే తుభ్యం మయోభవ నమోఽస్తు తే || ౩౭ ||\n",
      "\n",
      "మయస్కర నమస్తుభ్యం శంకరాయ నమో నమః |\n",
      "నమః శివాయ శర్వాయ నమః శివతరాయ చ || ౩౮ ||\n",
      "\n",
      "నమస్తీర్థ్యాయ కూల్యాయ నమః పార్యాయ తే నమః |\n",
      "ఆవార్యాయ నమస్తేఽస్తు నమః ప్రతరణాయ చ || ౩౯ ||\n",
      "\n",
      "నమ ఉత్తరణాయాఽపి హరాతార్యాయ తే నమః |\n",
      "ఆలాద్యాయ నమస్తేఽస్తు భక్తానాం వరదాయ చ || ౪౦ ||\n",
      "\n",
      "నమః శష్ప్యాయ ఫేన్యాయ సికత్యాయ నమో నమః |\n",
      "ప్రవాహ్యాయ నమస్తేఽస్తు హ్రస్వాయాఽస్తు నమో నమః || ౪౧ ||\n",
      "\n",
      "వామనాయ నమస్తేఽస్తు బృహతే చ నమో నమః |\n",
      "వర్షీయసే నమస్తేఽస్తు నమో వృద్ధాయ తే నమః || ౪౨ ||\n",
      "\n",
      "సంవృధ్వనే నమస్తుభ్యమగ్రియాయ నమో నమః |\n",
      "ప్రథమాయ నమస్తుభ్యమాశవే చాజిరాయ చ || ౪౩ ||\n",
      "\n",
      "శీఘ్రియాయ నమస్తేఽస్తు శీభ్యాయ చ నమో నమః |\n",
      "నమ ఊర్మ్యాయ శర్వాయాఽప్యవస్వన్యాయ తే నమః || ౪౪ ||\n",
      "\n",
      "స్రోతస్యాయ నమస్తుభ్యం ద్వీప్యాయ చ నమో నమః |\n",
      "జ్యేష్ఠాయ చ నమస్తుభ్యం కనిష్ఠాయ నమో నమః || ౪౫ ||\n",
      "\n",
      "పూర్వజాయ నమస్తుభ్యం నమోస్త్వపరజాయ చ |\n",
      "మధ్యమాయ నమస్తుభ్యమపగల్భాయ తే నమః || ౪౬ ||\n",
      "\n",
      "జఘన్యాయ నమస్తుభ్యం బుధ్నియాయ నమో నమః |\n",
      "సోభ్యాయ ప్రతిసర్యాయ యామ్యాయ చ నమో నమః || ౪౭ ||\n",
      "\n",
      "క్షేమ్యాయ చ నమస్తుభ్యం యామ్యాయ చ నమో నమః |\n",
      "ఉర్వర్యాయ నమస్తుభ్యం ఖల్యాయ చ నమో నమః || ౪౮ ||\n",
      "\n",
      "శ్లోక్యాయ చావసాన్యాయావస్వన్యాయ చ తే నమః |\n",
      "నమో వన్యాయ కక్ష్యాయ మౌంజ్యాయ చ నమో నమః || ౪౯ ||\n",
      "\n",
      "శ్రవాయ చ నమస్తుభ్యం ప్రతిశ్రవ నమో నమః |\n",
      "ఆశుషేణాయ శూరాయ నమోస్త్వాఽశురథాయ చ || ౫౦ ||\n",
      "\n",
      "వరూథినే పర్మిణే చ బిల్మినే చ నమో నమః |\n",
      "శ్రుతాయ శ్రుతసేనాయ నమః కవచినే నమః || ౫౧ ||\n",
      "\n",
      "దుందుభ్యాయ నమస్తుభ్యమాహనన్యాయ తే నమః |\n",
      "ప్రహితాయ నమస్తుభ్యం ధృష్ణవే ప్రమృశాయ చ || ౫౨ ||\n",
      "\n",
      "పారాయ పారవిందాయ నమస్తీక్ష్ణేషవే నమః |\n",
      "సుధన్వనే నమస్తుభ్యం స్వాయుధాయ నమో నమః || ౫౩ ||\n",
      "\n",
      "నమః స్రుత్యాయ పథ్యాయ నమః కాట్యాయ తే నమః |\n",
      "నమో నీప్యాయ సూద్యాయ సరస్యాయ చ తే నమః || ౫౪ ||\n",
      "\n",
      "నమో నాద్యాయ భవ్యాయ వైశంతాయ నమో నమః |\n",
      "అవట్యాయ నమస్తుభ్యం నమః కూప్యాయ తే నమః || ౫౫ ||\n",
      "\n",
      "అవర్ష్యాయ చ వర్ష్యాయ మేఘ్యాయ చ నమో నమః |\n",
      "విద్యుత్యాయ నమస్తుభ్యమీధ్రియాయ నమో నమః || ౫౬ ||\n",
      "\n",
      "ఆతప్యాయ నమస్తుభ్యం వాత్యాయ చ నమో నమః |\n",
      "రేష్మియాయ నమస్తుభ్యం వాస్తవ్యాయ చ తే నమః || ౫౭ ||\n",
      "\n",
      "వాస్తుపాయ నమస్తుభ్యం నమః సోమాయ తే నమః |\n",
      "నమో రుద్రాయ తామ్రాయాఽప్యరుణాయ చ తే నమః || ౫౮ ||\n",
      "\n",
      "నమ ఉగ్రాయ భీమాయ నమః శంగాయ తే నమః |\n",
      "నమస్తీర్థ్యాయ కూల్యాయ సికత్యాయ నమో నమః || ౫౯ ||\n",
      "\n",
      "ప్రవాహ్యాయ నమస్తుభ్యమిరిణ్యాయ నమో నమః |\n",
      "నమస్తే చంద్రచూడాయ ప్రపథ్యాయ నమో నమః || ౬౦ ||\n",
      "\n",
      "కింశిలాయ నమస్తేఽస్తు క్షయణాయ చ తే నమః |\n",
      "కపర్దినే నమస్తేఽస్తు నమస్తేఽస్తు పులస్తయే || ౬౧ ||\n",
      "\n",
      "నమో గోష్ఠ్యాయ గృహ్యాయ గ్రహాణాం పతయే నమః |\n",
      "నమస్తల్ప్యాయ గేహ్యాయ గుహావాసాయ తే నమః || ౬౨ ||\n",
      "\n",
      "కాట్యాయ గహ్వరేష్ఠాయ హ్రదయ్యాయ చ తే నమః |\n",
      "నివేష్ప్యాయ నమస్తుభ్యం పాంసవ్యాయ తే నమః || ౬౩ ||\n",
      "\n",
      "రజస్యాయ నమస్తుభ్యం పరాత్పర తరాయ చ |\n",
      "నమస్తే హరికేశాయ శుష్క్యాయ చ నమో నమః || ౬౪ ||\n",
      "\n",
      "హరిత్యాయ నమస్తుభ్యం హరిద్వర్ణాయ తే నమః |\n",
      "నమః ఉర్మ్యాయ సూర్మ్యాయ పర్ణ్యాయ చ నమో నమః || ౬౫ ||\n",
      "\n",
      "నమోపగురమాణాయ పర్ణశద్యాయ తే నమః |\n",
      "అభిఘ్నతే చాఖ్ఖిదతే నమః ప్రఖ్ఖిదతే నమః || ౬౬ ||\n",
      "\n",
      "విశ్వరూపాయ విశ్వాయ విశ్వాధారాయ తే నమః |\n",
      "త్ర్యంబకాయ చ రుద్రాయ గిరిజాపతయే నమః || ౬౭ ||\n",
      "\n",
      "మణికోటీరకోటిస్థ కాంతిదీప్తాయ తే నమః |\n",
      "వేదవేదాంత వేద్యాయ వృషారూఢాయ తే నమః || ౬౮ ||\n",
      "\n",
      "అవిజ్ఞేయస్వరూపాయ సుందరాయ నమో నమః |\n",
      "ఉమాకాంత నమస్తేఽస్తు నమస్తే సర్వసాక్షిణే || ౬౯ ||\n",
      "\n",
      "హిరణ్యబాహవే తుభ్యం హిరణ్యాభరణాయ చ |\n",
      "నమో హిరణ్యరూపాయ రూపాతీతాయ తే నమః || ౭౦ ||\n",
      "\n",
      "హిరణ్యపతయే తుభ్యమంబికాపతయే నమః |\n",
      "ఉమాయాః పతయే తుభ్యం నమః పాపప్రణాశక || ౭౧ ||\n",
      "\n",
      "మీఢుష్టమాయ దుర్గాయ కద్రుద్రాయ ప్రచేతసే |\n",
      "తవ్యసే బిల్వపూజ్యాయ నమః కళ్యాణరూపిణే || ౭౨ ||\n",
      "\n",
      "అపార కళ్యాణ గుణార్ణవాయ\n",
      "శ్రీ నీలకంఠాయ నిరంజనాయ |\n",
      "కాలాంతకాయాపి నమో నమస్తే\n",
      "దిక్కాలరూపాయ నమో నమస్తే || ౭౩ ||\n",
      "\n",
      "వేదాంతబృందస్తుత సద్గుణాయ\n",
      "గుణప్రవీణాయ గుణాశ్రయాయ |\n",
      "శ్రీ విశ్వనాథాయ నమో నమస్తే\n",
      "కాశీనివాసాయ నమో నమస్తే || ౭౪ ||\n",
      "\n",
      "అమేయ సౌందర్య సుధానిధాన\n",
      "సమృద్ధిరూపాయ నమో నమస్తే |\n",
      "ధరాధరాకార నమో నమస్తే\n",
      "ధారాస్వరూపాయ నమో నమస్తే || ౭౫ ||\n",
      "\n",
      "నీహార శైలాత్మజ హృద్విహార\n",
      "ప్రకాశహార ప్రవిభాసి వీర |\n",
      "వీరేశ్వరాపార దయానిధాన\n",
      "పాహి ప్రభో పాహి నమో నమస్తే || ౭౬ ||\n",
      "\n",
      "వ్యాస ఉవాచ |\n",
      "ఏవం స్తుత్వా మహాదేవం ప్రణిపత్య పునః పునః |\n",
      "కృతాంజలిపుటస్తస్థౌ పార్శ్వే డుంఠివినాయకః || ౭౭ ||\n",
      "\n",
      "తమాలోక్య సుతం ప్రాప్తం వేదం వేదాంగపారగమ్ |\n",
      "స్నేహాశ్రుధారా సంవీతం ప్రాహ డుంఠిం సదాశివః || ౭౮ ||\n",
      "\n",
      "ఇతి శ్రీ శివరహస్యే హరాఖ్యే తృతీయాంశే పూర్వార్థే గణేశకృత రుద్రాధ్యాయ స్తుతిః నామ దశమోఽధ్యాయః |\n",
      "అనేన శ్రీగణేశకృత శ్లోకాత్మక రుద్రధ్యాయ పారాయణేన శ్రీ విశ్వేశ్వరః సుప్రీతః సుప్రసన్నో వరదో భవతు |\n"
],
    "en": [
      "dhyānam |\n",
      "āpātāla nabhaḥ sthalānta bhuvana brahmāṇḍamāvisphura-\n",
      "-jjyōtiḥsphāṭikaliṅga maulivilasat pūrṇēndu vāntāmr̥taiḥ |\n",
      "astōkāplutamēkamīśamaniśaṁ rudrānuvākān japan\n",
      "dhyāyēdīpsitasiddhayē dhruvapadaṁ viprō:'bhiṣiñcēcchivam ||\n",
      "\n",
      "brahmāṇḍavyāptadēhā bhasita himarucā bhāsamānā bhujaṅgaiḥ\n",
      "kaṇṭhē kālāḥ kapardāḥ kalitaśaśikalāścaṇḍa kōdaṇḍa hastāḥ |\n",
      "tryakṣā rudrākṣamālāḥ sulalitavapuṣaḥ śāmbhavā mūrtibhēdāḥ\n",
      "rudrāḥ śrīrudrasūkta prakaṭita vibhavāḥ naḥ prayacchantu saukhyam ||\n",
      "\n",
      "ityuktvā satvaraṁ sāmbaṁ smr̥tvā śaṅkarapādukē |\n",
      "dhyātvā yayau gaṇādhīśaḥ śivasannidhimādarāt ||\n",
      "\n",
      "tataḥ praṇamya bahudhā kr̥tāñjalipuṭaḥ prabhum |\n",
      "śambhuṁ stōtuṁ matiṁ cakrē sarvābhīṣṭapradāyakam ||\n",
      "\n",
      "gaṇēśa uvāca |\n",
      "namastē dēvadēvāya namastē rudramanyavē |\n",
      "namastē candracūḍāyāpyutōta iṣavē namaḥ || 1 ||\n",
      "\n",
      "namastē pārvatīkāntāyaikarūpāya dhanvanē |\n",
      "namastē bhagavan śambhō bāhubhyāmuta tē namaḥ || 2 ||\n",
      "\n",
      "iṣuḥ śivatamā yā tē tayā mr̥ḍāya rudra mām |\n",
      "śivaṁ dhanuryadbabhūva tēnāpi mr̥ḍayādhunā || 3 ||\n",
      "\n",
      "śaravyā yā śivatamā tayāpi mr̥ḍaya prabhō |\n",
      "yā tē rudra śivā nityaṁ sarvamaṅgalasādhanam || 4 ||\n",
      "\n",
      "tayābhicākaśīhi tvaṁ tanuvā māmumāpatē |\n",
      "aghōrayāpi tanuvā rudrādyāpāpakāśinī || 5 ||\n",
      "\n",
      "yā tayā mr̥ḍaya svāmin sadā śantamayā prabhō |\n",
      "giriśantaṁ mahārudra hastē yāmiṣumastavē || 6 ||\n",
      "\n",
      "bibharṣi tāṁ giritrādya śivāṁ kuru śivāpatē |\n",
      "śivēna vacasā rudra nityaṁ vācā vadāmasi || 7 ||\n",
      "\n",
      "tvadbhakti paripūtāṅgaṁ mahiṁsīḥ puruṣaṁ jagat |\n",
      "yacca śarva jagatsarvamayakṣmaṁ sumanā asat || 8 ||\n",
      "\n",
      "yathā tathāvamāṁ rudra tadanyadhāpi mē prabhō |\n",
      "rudra tvaṁ prathamō daivyō bhiṣak pāpavināśakaḥ || 9 ||\n",
      "\n",
      "adhivaktā:'dhyavōcanmāṁ bhāvaliṅgārcakaṁ mudā |\n",
      "ahīn sarvān yātu dhānyaḥ sarvā apyadya jambhayan || 10 ||\n",
      "\n",
      "asau tāmrōruṇō babhruḥ nīlagrīvaḥ sumaṅgalaḥ |\n",
      "vilōhitōstvayaṁ śambhō tvadadhiṣṭhāna ēva hi || 11 ||\n",
      "\n",
      "namō namastē bhagavan nīlagrīvāya mīḍhuṣē |\n",
      "sahasrākṣāya śuddhāya saccidānandamūrtayē || 12 ||\n",
      "\n",
      "ubhayōgārtniyōrjyā yā dhanvanastāṁ pramuñcatām |\n",
      "samprāpya dhanuranyēṣāṁ bhayāya prabhaviṣyati || 13 ||\n",
      "\n",
      "asmadbhaya vināśārtha madhunābhayada prabhō |\n",
      "yāśca tē hasta iṣavaḥ paratā bhagavō vāpa || 14 ||\n",
      "\n",
      "avatatya dhanuśca tvaṁ sahasrākṣa śatēṣudhē |\n",
      "mukhā niśīrya śalyānāṁ śivō naḥ sumanā bhava || 15 ||\n",
      "\n",
      "vijyaṁ dhanuridaṁ bhūyāt viśalyō bāṇavānapi |\n",
      "anēśanniṣavaścāpi hyābhurastu niṣaṅgathiḥ || 16 ||\n",
      "\n",
      "kapardinō mahēśasya yadi nābhurniṣaṅgathiḥ |\n",
      "iṣavō pi samarthāścēt sāmarthyētu bhayaṁ bhavēt || 17 ||\n",
      "\n",
      "yā tē hētirdhanurhastē mīḍhuṣṭama babhūva yā |\n",
      "tayā:'smān viśvatastēna pālaya tvamayakṣmayā || 18 ||\n",
      "\n",
      "anātatāyāyudhāya namastē dhr̥ṣṇavē namaḥ |\n",
      "bāhubhyāṁ dhanvanē śambhō namō bhūyō namō namaḥ || 19 ||\n",
      "\n",
      "paritē dhanvanō hētiḥ viśvatō:'smān vr̥ṇaktu naḥ |\n",
      "iṣudhistava yā tāvadasmadārē nidhēhi tam || 20 ||\n",
      "\n",
      "hiraṇyabāhavē tubhyaṁ sēnānyē tē namō namaḥ |\n",
      "diśāṁ ca patayē tubhyaṁ paśūnāṁ patayē namaḥ || 21 ||\n",
      "\n",
      "tviṣīmatē namastubhyaṁ namaḥ saspiñjarāya tē |\n",
      "namaḥ pathīnāṁ patayē babhluśāya namō namaḥ || 22 ||\n",
      "\n",
      "namō vivyādhinēnnānāṁ patayē prabhavē namaḥ |\n",
      "namastē harikēśāya rudrāyāstūpavītinē || 23 ||\n",
      "\n",
      "puṣṭānāṁ patayē tubhyaṁ jagatāṁ patayē namaḥ |\n",
      "saṁsāra hēti rūpāya rudrāyāpyātatāyinē || 24 ||\n",
      "\n",
      "kṣētrāṇāṁ patayē tubhyaṁ sūtāya sukr̥tātmanē |\n",
      "ahantyāya namastubhyaṁ vanānāṁ patayē namaḥ || 25 ||\n",
      "\n",
      "rōhitāya sthapatayē mantriṇē vāṇijāya ca |\n",
      "kakṣāṇāṁ patayē tubhyaṁ namastubhyaṁ bhuvantayē || 26 ||\n",
      "\n",
      "tadvārivaskr̥tāyāstu mahādēvāya tē namaḥ |\n",
      "ōṣādhīnāṁ ca patayē namastubhyaṁ mahātmanē || 27 ||\n",
      "\n",
      "uccairghōṣāya dhīrāya dhīrān krandayatē namaḥ || 28 ||\n",
      "\n",
      "pattīnāṁ patayē tubhyaṁ kr̥tsnavītāya tē namaḥ |\n",
      "dhāvatē dhavalāyāpi sattvanāṁ patayē namaḥ || 29 ||\n",
      "\n",
      "āvyādhinīnāṁ patayē kakubhāya niṣaṅgiṇē |\n",
      "stēnānāṁ patayē tubhyaṁ divyēṣudhimatē namaḥ || 30 ||\n",
      "\n",
      "taskarāṇāṁ ca patayē vañcatē parivañcatē |\n",
      "stāyūnāṁ patayē tubhyaṁ namastē:'stu nicēravē || 31 ||\n",
      "\n",
      "namaḥ paricarāyā:'pi mahārudrāya tē namaḥ |\n",
      "araṇyānāṁ ca patayē muṣṇatāṁ patayē namaḥ || 32 ||\n",
      "\n",
      "uṣṇīṣiṇē namastubhyaṁ namō giricarāya tē |\n",
      "kuluñcānāṁ ca patayē namastubhyaṁ bhavāya ca || 33 ||\n",
      "\n",
      "namō rudrāya śarvāya tubhyaṁ paśupatē namaḥ |\n",
      "nama ugrāya bhīmāya namaścāgrēvadhāya ca || 34 ||\n",
      "\n",
      "namō dūrēvadhāyā:'pi namō hantrē namō namaḥ |\n",
      "hanīyasē namastubhyaṁ nīlagrīvāya tē namaḥ || 35 ||\n",
      "\n",
      "namastē śitikaṇṭhāya namastē:'stu kapardinē |\n",
      "namastē vyuptakēśāya sahasrākṣāya mīḍhuṣē || 36 ||\n",
      "\n",
      "giriśāya namastē:'stu śipiviṣṭāya tē namaḥ |\n",
      "namastē śambhavē tubhyaṁ mayōbhava namō:'stu tē || 37 ||\n",
      "\n",
      "mayaskara namastubhyaṁ śaṅkarāya namō namaḥ |\n",
      "namaḥ śivāya śarvāya namaḥ śivatarāya ca || 38 ||\n",
      "\n",
      "namastīrthyāya kūlyāya namaḥ pāryāya tē namaḥ |\n",
      "āvāryāya namastē:'stu namaḥ prataraṇāya ca || 39 ||\n",
      "\n",
      "nama uttaraṇāyā:'pi harātāryāya tē namaḥ |\n",
      "ālādyāya namastē:'stu bhaktānāṁ varadāya ca || 40 ||\n",
      "\n",
      "namaḥ śaṣpyāya phēnyāya sikatyāya namō namaḥ |\n",
      "pravāhyāya namastē:'stu hrasvāyā:'stu namō namaḥ || 41 ||\n",
      "\n",
      "vāmanāya namastē:'stu br̥hatē ca namō namaḥ |\n",
      "varṣīyasē namastē:'stu namō vr̥ddhāya tē namaḥ || 42 ||\n",
      "\n",
      "saṁvr̥dhvanē namastubhyamagriyāya namō namaḥ |\n",
      "prathamāya namastubhyamāśavē cājirāya ca || 43 ||\n",
      "\n",
      "śīghriyāya namastē:'stu śībhyāya ca namō namaḥ |\n",
      "nama ūrmyāya śarvāyā:'pyavasvanyāya tē namaḥ || 44 ||\n",
      "\n",
      "srōtasyāya namastubhyaṁ dvīpyāya ca namō namaḥ |\n",
      "jyēṣṭhāya ca namastubhyaṁ kaniṣṭhāya namō namaḥ || 45 ||\n",
      "\n",
      "pūrvajāya namastubhyaṁ namōstvaparajāya ca |\n",
      "madhyamāya namastubhyamapagalbhāya tē namaḥ || 46 ||\n",
      "\n",
      "jaghanyāya namastubhyaṁ budhniyāya namō namaḥ |\n",
      "sōbhyāya pratisaryāya yāmyāya ca namō namaḥ || 47 ||\n",
      "\n",
      "kṣēmyāya ca namastubhyaṁ yāmyāya ca namō namaḥ |\n",
      "urvaryāya namastubhyaṁ khalyāya ca namō namaḥ || 48 ||\n",
      "\n",
      "ślōkyāya cāvasānyāyāvasvanyāya ca tē namaḥ |\n",
      "namō vanyāya kakṣyāya mauñjyāya ca namō namaḥ || 49 ||\n",
      "\n",
      "śravāya ca namastubhyaṁ pratiśrava namō namaḥ |\n",
      "āśuṣēṇāya śūrāya namōstvā:'śurathāya ca || 50 ||\n",
      "\n",
      "varūthinē parmiṇē ca bilminē ca namō namaḥ |\n",
      "śrutāya śrutasēnāya namaḥ kavacinē namaḥ || 51 ||\n",
      "\n",
      "dundubhyāya namastubhyamāhananyāya tē namaḥ |\n",
      "prahitāya namastubhyaṁ dhr̥ṣṇavē pramr̥śāya ca || 52 ||\n",
      "\n",
      "pārāya pāravindāya namastīkṣṇēṣavē namaḥ |\n",
      "sudhanvanē namastubhyaṁ svāyudhāya namō namaḥ || 53 ||\n",
      "\n",
      "namaḥ srutyāya pathyāya namaḥ kāṭyāya tē namaḥ |\n",
      "namō nīpyāya sūdyāya sarasyāya ca tē namaḥ || 54 ||\n",
      "\n",
      "namō nādyāya bhavyāya vaiśantāya namō namaḥ |\n",
      "avaṭyāya namastubhyaṁ namaḥ kūpyāya tē namaḥ || 55 ||\n",
      "\n",
      "avarṣyāya ca varṣyāya mēghyāya ca namō namaḥ |\n",
      "vidyutyāya namastubhyamīdhriyāya namō namaḥ || 56 ||\n",
      "\n",
      "ātapyāya namastubhyaṁ vātyāya ca namō namaḥ |\n",
      "rēṣmiyāya namastubhyaṁ vāstavyāya ca tē namaḥ || 57 ||\n",
      "\n",
      "vāstupāya namastubhyaṁ namaḥ sōmāya tē namaḥ |\n",
      "namō rudrāya tāmrāyā:'pyaruṇāya ca tē namaḥ || 58 ||\n",
      "\n",
      "nama ugrāya bhīmāya namaḥ śaṅgāya tē namaḥ |\n",
      "namastīrthyāya kūlyāya sikatyāya namō namaḥ || 59 ||\n",
      "\n",
      "pravāhyāya namastubhyamiriṇyāya namō namaḥ |\n",
      "namastē candracūḍāya prapathyāya namō namaḥ || 60 ||\n",
      "\n",
      "kiṁśilāya namastē:'stu kṣayaṇāya ca tē namaḥ |\n",
      "kapardinē namastē:'stu namastē:'stu pulastayē || 61 ||\n",
      "\n",
      "namō gōṣṭhyāya gr̥hyāya grahāṇāṁ patayē namaḥ |\n",
      "namastalpyāya gēhyāya guhāvāsāya tē namaḥ || 62 ||\n",
      "\n",
      "kāṭyāya gahvarēṣṭhāya hradayyāya ca tē namaḥ |\n",
      "nivēṣpyāya namastubhyaṁ pāṁsavyāya tē namaḥ || 63 ||\n",
      "\n",
      "rajasyāya namastubhyaṁ parātpara tarāya ca |\n",
      "namastē harikēśāya śuṣkyāya ca namō namaḥ || 64 ||\n",
      "\n",
      "harityāya namastubhyaṁ haridvarṇāya tē namaḥ |\n",
      "namaḥ urmyāya sūrmyāya parṇyāya ca namō namaḥ || 65 ||\n",
      "\n",
      "namōpaguramāṇāya parṇaśadyāya tē namaḥ |\n",
      "abhighnatē cākhkhidatē namaḥ prakhkhidatē namaḥ || 66 ||\n",
      "\n",
      "viśvarūpāya viśvāya viśvādhārāya tē namaḥ |\n",
      "tryambakāya ca rudrāya girijāpatayē namaḥ || 67 ||\n",
      "\n",
      "maṇikōṭīrakōṭistha kāntidīptāya tē namaḥ |\n",
      "vēdavēdānta vēdyāya vr̥ṣārūḍhāya tē namaḥ || 68 ||\n",
      "\n",
      "avijñēyasvarūpāya sundarāya namō namaḥ |\n",
      "umākānta namastē:'stu namastē sarvasākṣiṇē || 69 ||\n",
      "\n",
      "hiraṇyabāhavē tubhyaṁ hiraṇyābharaṇāya ca |\n",
      "namō hiraṇyarūpāya rūpātītāya tē namaḥ || 70 ||\n",
      "\n",
      "hiraṇyapatayē tubhyamambikāpatayē namaḥ |\n",
      "umāyāḥ patayē tubhyaṁ namaḥ pāpapraṇāśaka || 71 ||\n",
      "\n",
      "mīḍhuṣṭamāya durgāya kadrudrāya pracētasē |\n",
      "tavyasē bilvapūjyāya namaḥ kalyāṇarūpiṇē || 72 ||\n",
      "\n",
      "apāra kalyāṇa guṇārṇavāya\n",
      "śrī nīlakaṇṭhāya nirañjanāya |\n",
      "kālāntakāyāpi namō namastē\n",
      "dikkālarūpāya namō namastē || 73 ||\n",
      "\n",
      "vēdāntabr̥ndastuta sadguṇāya\n",
      "guṇapravīṇāya guṇāśrayāya |\n",
      "śrī viśvanāthāya namō namastē\n",
      "kāśīnivāsāya namō namastē || 74 ||\n",
      "\n",
      "amēya saundarya sudhānidhāna\n",
      "samr̥ddhirūpāya namō namastē |\n",
      "dharādharākāra namō namastē\n",
      "dhārāsvarūpāya namō namastē || 75 ||\n",
      "\n",
      "nīhāra śailātmaja hr̥dvihāra\n",
      "prakāśahāra pravibhāsi vīra |\n",
      "vīrēśvarāpāra dayānidhāna\n",
      "pāhi prabhō pāhi namō namastē || 76 ||\n",
      "\n",
      "vyāsa uvāca |\n",
      "ēvaṁ stutvā mahādēvaṁ praṇipatya punaḥ punaḥ |\n",
      "kr̥tāñjalipuṭastasthau pārśvē ḍuṇṭhivināyakaḥ || 77 ||\n",
      "\n",
      "tamālōkya sutaṁ prāptaṁ vēdaṁ vēdāṅgapāragam |\n",
      "snēhāśrudhārā saṁvītaṁ prāha ḍuṇṭhiṁ sadāśivaḥ || 78 ||\n",
      "\n",
      "iti śrī śivarahasyē harākhyē tr̥tīyāṁśē pūrvārthē gaṇēśakr̥ta rudrādhyāya stutiḥ nāma daśamō:'dhyāyaḥ |\n",
      "anēna śrīgaṇēśakr̥ta ślōkātmaka rudradhyāya pārāyaṇēna śrī viśvēśvaraḥ suprītaḥ suprasannō varadō bhavatu |\n"
],
    "hi": [
      "ध्यानम् ।\n",
      "आपाताल नभः स्थलान्त भुवन ब्रह्माण्डमाविस्फुर-\n",
      "-ज्ज्योतिःस्फाटिकलिङ्ग मौलिविलसत् पूर्णेन्दु वान्तामृतैः ।\n",
      "अस्तोकाप्लुतमेकमीशमनिशं रुद्रानुवाकान् जपन्\n",
      "ध्यायेदीप्सितसिद्धये ध्रुवपदं विप्रोऽभिषिञ्चेच्छिवम् ॥\n",
      "\n",
      "ब्रह्माण्डव्याप्तदेहा भसित हिमरुचा भासमाना भुजङ्गैः\n",
      "कण्ठे कालाः कपर्दाः कलितशशिकलाश्चण्ड कोदण्ड हस्ताः ।\n",
      "त्र्यक्षा रुद्राक्षमालाः सुललितवपुषः शाम्भवा मूर्तिभेदाः\n",
      "रुद्राः श्रीरुद्रसूक्त प्रकटित विभवाः नः प्रयच्छन्तु सौख्यम् ॥\n",
      "\n",
      "इत्युक्त्वा सत्वरं साम्बं स्मृत्वा शङ्करपादुके ।\n",
      "ध्यात्वा ययौ गणाधीशः शिवसन्निधिमादरात् ॥\n",
      "\n",
      "ततः प्रणम्य बहुधा कृताञ्जलिपुटः प्रभुम् ।\n",
      "शम्भुं स्तोतुं मतिं चक्रे सर्वाभीष्टप्रदायकम् ॥\n",
      "\n",
      "गणेश उवाच ।\n",
      "नमस्ते देवदेवाय नमस्ते रुद्रमन्यवे ।\n",
      "नमस्ते चन्द्रचूडायाप्युतोत इषवे नमः ॥ १ ॥\n",
      "\n",
      "नमस्ते पार्वतीकान्तायैकरूपाय धन्वने ।\n",
      "नमस्ते भगवन् शम्भो बाहुभ्यामुत ते नमः ॥ २ ॥\n",
      "\n",
      "इषुः शिवतमा या ते तया मृडाय रुद्र माम् ।\n",
      "शिवं धनुर्यद्बभूव तेनापि मृडयाधुना ॥ ३ ॥\n",
      "\n",
      "शरव्या या शिवतमा तयापि मृडय प्रभो ।\n",
      "या ते रुद्र शिवा नित्यं सर्वमङ्गलसाधनम् ॥ ४ ॥\n",
      "\n",
      "तयाभिचाकशीहि त्वं तनुवा मामुमापते ।\n",
      "अघोरयापि तनुवा रुद्राद्या पापकाशिनी ॥ ५ ॥\n",
      "\n",
      "या तया मृडय स्वामिन् सदा शन्तमया प्रभो ।\n",
      "गिरिशन्तं महारुद्र हस्ते यामिषुमस्तवे ॥ ६ ॥\n",
      "\n",
      "बिभर्षि तां गिरित्राद्य शिवां कुरु शिवापते ।\n",
      "शिवेन वचसा रुद्र नित्यं वाचा वदामसि ॥ ७ ॥\n",
      "\n",
      "त्वद्भक्ति परिपूताङ्गं महिंसीः पुरुषं जगत् ।\n",
      "यच्च शर्व जगत्सर्वमयक्ष्मं सुमना असत् ॥ ८ ॥\n",
      "\n",
      "यथा तथावमां रुद्र तदन्यधापि मे प्रभो ।\n",
      "रुद्र त्वं प्रथमो दैव्यो भिषक् पापविनाशकः ॥ ९ ॥\n",
      "\n",
      "अधिवक्ताऽध्यवोचन्मां भावलिङ्गार्चकं मुदा ।\n",
      "अहीन् सर्वान् यातु धान्यः सर्वा अप्यद्य जम्भयन् ॥ १० ॥\n",
      "\n",
      "असौ ताम्रोरुणो बभ्रुः नीलग्रीवः सुमङ्गलः ।\n",
      "विलोहितोस्त्वयं शम्भो त्वदधिष्ठान एव हि ॥ ११ ॥\n",
      "\n",
      "नमो नमस्ते भगवन् नीलग्रीवाय मीढुषे ।\n",
      "सहस्राक्षाय शुद्धाय सच्चिदानन्दमूर्तये ॥ १२ ॥\n",
      "\n",
      "उभयोगार्त्नियोर्ज्या या धन्वनस्तां प्रमुञ्चताम् ।\n",
      "सम्प्राप्य धनुरन्येषां भयाय प्रभविष्यति ॥ १३ ॥\n",
      "\n",
      "अस्मद्भय विनाशार्थ मधुनाभयद प्रभो ।\n",
      "याश्च ते हस्त इषवः परता भगवो वाप ॥ १४ ॥\n",
      "\n",
      "अवतत्य धनुश्च त्वं सहस्राक्ष शतेषुधे ।\n",
      "मुखा निशीर्य शल्यानां शिवो नः सुमना भव ॥ १५ ॥\n",
      "\n",
      "विज्यं धनुरिदं भूयात् विशल्यो बाणवानपि ।\n",
      "अनेशन्निषवश्चापि ह्याभुरस्तु निषङ्गथिः ॥ १६ ॥\n",
      "\n",
      "कपर्दिनो महेशस्य यदि नाभुर्निषङ्गथिः ।\n",
      "इषवो पि समर्थाश्चेत् सामर्थ्येतु भयं भवेत् ॥ १७ ॥\n",
      "\n",
      "या ते हेतिर्धनुर्हस्ते मीढुष्टम बभूव या ।\n",
      "तयाऽस्मान् विश्वतस्तेन पालय त्वमयक्ष्मया ॥ १८ ॥\n",
      "\n",
      "अनाततायायुधाय नमस्ते धृष्णवे नमः ।\n",
      "बाहुभ्यां धन्वने शम्भो नमो भूयो नमो नमः ॥ १९ ॥\n",
      "\n",
      "परिते धन्वनो हेतिः विश्वतोऽस्मान् वृणक्तु नः ।\n",
      "इषुधिस्तव या तावदस्मदारे निधेहि तम् ॥ २० ॥\n",
      "\n",
      "हिरण्यबाहवे तुभ्यं सेनान्ये ते नमो नमः ।\n",
      "दिशां च पतये तुभ्यं पशूनां पतये नमः ॥ २१ ॥\n",
      "\n",
      "त्विषीमते नमस्तुभ्यं नमः सस्पिञ्जराय ते ।\n",
      "नमः पथीनां पतये बभ्लुशाय नमो नमः ॥ २२ ॥\n",
      "\n",
      "नमो विव्याधिनेन्नानां पतये प्रभवे नमः ।\n",
      "नमस्ते हरिकेशाय रुद्रायास्तूपवीतिने ॥ २३ ॥\n",
      "\n",
      "पुष्टानां पतये तुभ्यं जगतां पतये नमः ।\n",
      "संसार हेति रूपाय रुद्रायाप्याततायिने ॥ २४ ॥\n",
      "\n",
      "क्षेत्राणां पतये तुभ्यं सूताय सुकृतात्मने ।\n",
      "अहन्त्याय नमस्तुभ्यं वनानां पतये नमः ॥ २५ ॥\n",
      "\n",
      "रोहिताय स्थपतये मन्त्रिणे वाणिजाय च ।\n",
      "कक्षाणां पतये तुभ्यं नमस्तुभ्यं भुवन्तये ॥ २६ ॥\n",
      "\n",
      "तद्वारिवस्कृतायास्तु महादेवाय ते नमः ।\n",
      "ओषाधीनां च पतये नमस्तुभ्यं महात्मने ॥ २७ ॥\n",
      "\n",
      "उच्चैर्घोषाय धीराय धीरान् क्रन्दयते नमः ॥ २८ ॥\n",
      "\n",
      "पत्तीनां पतये तुभ्यं कृत्स्नवीताय ते नमः ।\n",
      "धावते धवलायापि सत्त्वनां पतये नमः ॥ २९ ॥\n",
      "\n",
      "आव्याधिनीनां पतये ककुभाय निषङ्गिणे ।\n",
      "स्तेनानां पतये तुभ्यं दिव्येषुधिमते नमः ॥ ३० ॥\n",
      "\n",
      "तस्कराणां च पतये वञ्चते परिवञ्चते ।\n",
      "स्तायूनां पतये तुभ्यं नमस्तेऽस्तु निचेरवे ॥ ३१ ॥\n",
      "\n",
      "नमः परिचरायाऽपि महारुद्राय ते नमः ।\n",
      "अरण्यानां च पतये मुष्णतां पतये नमः ॥ ३२ ॥\n",
      "\n",
      "उष्णीषिणे नमस्तुभ्यं नमो गिरिचराय ते ।\n",
      "कुलुञ्चानां च पतये नमस्तुभ्यं भवाय च ॥ ३३ ॥\n",
      "\n",
      "नमो रुद्राय शर्वाय तुभ्यं पशुपते नमः ।\n",
      "नम उग्राय भीमाय नमश्चाग्रेवधाय च ॥ ३४ ॥\n",
      "\n",
      "नमो दूरेवधायाऽपि नमो हन्त्रे नमो नमः ।\n",
      "हनीयसे नमस्तुभ्यं नीलग्रीवाय ते नमः ॥ ३५ ॥\n",
      "\n",
      "नमस्ते शितिकण्ठाय नमस्तेऽस्तु कपर्दिने ।\n",
      "नमस्ते व्युप्तकेशाय सहस्राक्षाय मीढुषे ॥ ३६ ॥\n",
      "\n",
      "गिरिशाय नमस्तेऽस्तु शिपिविष्टाय ते नमः ।\n",
      "नमस्ते शम्भवे तुभ्यं मयोभव नमोऽस्तु ते ॥ ३७ ॥\n",
      "\n",
      "मयस्कर नमस्तुभ्यं शङ्कराय नमो नमः ।\n",
      "नमः शिवाय शर्वाय नमः शिवतराय च ॥ ३८ ॥\n",
      "\n",
      "नमस्तीर्थ्याय कूल्याय नमः पार्याय ते नमः ।\n",
      "आवार्याय नमस्तेऽस्तु नमः प्रतरणाय च ॥ ३९ ॥\n",
      "\n",
      "नम उत्तरणायाऽपि हरातार्याय ते नमः ।\n",
      "आलाद्याय नमस्तेऽस्तु भक्तानां वरदाय च ॥ ४० ॥\n",
      "\n",
      "नमः शष्प्याय फेन्याय सिकत्याय नमो नमः ।\n",
      "प्रवाह्याय नमस्तेऽस्तु ह्रस्वायाऽस्तु नमो नमः ॥ ४१ ॥\n",
      "\n",
      "वामनाय नमस्तेऽस्तु बृहते च नमो नमः ।\n",
      "वर्षीयसे नमस्तेऽस्तु नमो वृद्धाय ते नमः ॥ ४२ ॥\n",
      "\n",
      "संवृध्वने नमस्तुभ्यमग्रियाय नमो नमः ।\n",
      "प्रथमाय नमस्तुभ्यमाशवे चाजिराय च ॥ ४३ ॥\n",
      "\n",
      "शीघ्रियाय नमस्तेऽस्तु शीभ्याय च नमो नमः ।\n",
      "नम ऊर्म्याय शर्वायाऽप्यवस्वन्याय ते नमः ॥ ४४ ॥\n",
      "\n",
      "स्रोतस्याय नमस्तुभ्यं द्वीप्याय च नमो नमः ।\n",
      "ज्येष्ठाय च नमस्तुभ्यं कनिष्ठाय नमो नमः ॥ ४५ ॥\n",
      "\n",
      "पूर्वजाय नमस्तुभ्यं नमोस्त्वपरजाय च ।\n",
      "मध्यमाय नमस्तुभ्यमपगल्भाय ते नमः ॥ ४६ ॥\n",
      "\n",
      "जघन्याय नमस्तुभ्यं बुध्नियाय नमो नमः ।\n",
      "सोभ्याय प्रतिसर्याय याम्याय च नमो नमः ॥ ४७ ॥\n",
      "\n",
      "क्षेम्याय च नमस्तुभ्यं याम्याय च नमो नमः ।\n",
      "उर्वर्याय नमस्तुभ्यं खल्याय च नमो नमः ॥ ४८ ॥\n",
      "\n",
      "श्लोक्याय चावसान्यायावस्वन्याय च ते नमः ।\n",
      "नमो वन्याय कक्ष्याय मौञ्ज्याय च नमो नमः ॥ ४९ ॥\n",
      "\n",
      "श्रवाय च नमस्तुभ्यं प्रतिश्रव नमो नमः ।\n",
      "आशुषेणाय शूराय नमोस्त्वाऽशुरथाय च ॥ ५० ॥\n",
      "\n",
      "वरूथिने पर्मिणे च बिल्मिने च नमो नमः ।\n",
      "श्रुताय श्रुतसेनाय नमः कवचिने नमः ॥ ५१ ॥\n",
      "\n",
      "दुन्दुभ्याय नमस्तुभ्यमाहनन्याय ते नमः ।\n",
      "प्रहिताय नमस्तुभ्यं धृष्णवे प्रमृशाय च ॥ ५२ ॥\n",
      "\n",
      "पाराय पारविन्दाय नमस्तीक्ष्णेषवे नमः ।\n",
      "सुधन्वने नमस्तुभ्यं स्वायुधाय नमो नमः ॥ ५३ ॥\n",
      "\n",
      "नमः स्रुत्याय पथ्याय नमः काट्याय ते नमः ।\n",
      "नमो नीप्याय सूद्याय सरस्याय च ते नमः ॥ ५४ ॥\n",
      "\n",
      "नमो नाद्याय भव्याय वैशन्ताय नमो नमः ।\n",
      "अवट्याय नमस्तुभ्यं नमः कूप्याय ते नमः ॥ ५५ ॥\n",
      "\n",
      "अवर्ष्याय च वर्ष्याय मेघ्याय च नमो नमः ।\n",
      "विद्युत्याय नमस्तुभ्यमीध्रियाय नमो नमः ॥ ५६ ॥\n",
      "\n",
      "आतप्याय नमस्तुभ्यं वात्याय च नमो नमः ।\n",
      "रेष्मियाय नमस्तुभ्यं वास्तव्याय च ते नमः ॥ ५७ ॥\n",
      "\n",
      "वास्तुपाय नमस्तुभ्यं नमः सोमाय ते नमः ।\n",
      "नमो रुद्राय ताम्रायाऽप्यरुणाय च ते नमः ॥ ५८ ॥\n",
      "\n",
      "नम उग्राय भीमाय नमः शङ्गाय ते नमः ।\n",
      "नमस्तीर्थ्याय कूल्याय सिकत्याय नमो नमः ॥ ५९ ॥\n",
      "\n",
      "प्रवाह्याय नमस्तुभ्यमिरिण्याय नमो नमः ।\n",
      "नमस्ते चन्द्रचूडाय प्रपथ्याय नमो नमः ॥ ६० ॥\n",
      "\n",
      "किंशिलाय नमस्तेऽस्तु क्षयणाय च ते नमः ।\n",
      "कपर्दिने नमस्तेऽस्तु नमस्तेऽस्तु पुलस्तये ॥ ६१ ॥\n",
      "\n",
      "नमो गोष्ठ्याय गृह्याय ग्रहाणां पतये नमः ।\n",
      "नमस्तल्प्याय गेह्याय गुहावासाय ते नमः ॥ ६२ ॥\n",
      "\n",
      "काट्याय गह्वरेष्ठाय ह्रदय्याय च ते नमः ।\n",
      "निवेष्प्याय नमस्तुभ्यं पांसव्याय ते नमः ॥ ६३ ॥\n",
      "\n",
      "रजस्याय नमस्तुभ्यं परात्पर तराय च ।\n",
      "नमस्ते हरिकेशाय शुष्क्याय च नमो नमः ॥ ६४ ॥\n",
      "\n",
      "हरित्याय नमस्तुभ्यं हरिद्वर्णाय ते नमः ।\n",
      "नमः उर्म्याय सूर्म्याय पर्ण्याय च नमो नमः ॥ ६५ ॥\n",
      "\n",
      "नमोपगुरमाणाय पर्णशद्याय ते नमः ।\n",
      "अभिघ्नते चाख्खिदते नमः प्रख्खिदते नमः ॥ ६६ ॥\n",
      "\n",
      "विश्वरूपाय विश्वाय विश्वाधाराय ते नमः ।\n",
      "त्र्यम्बकाय च रुद्राय गिरिजापतये नमः ॥ ६७ ॥\n",
      "\n",
      "मणिकोटीरकोटिस्थ कान्तिदीप्ताय ते नमः ।\n",
      "वेदवेदान्त वेद्याय वृषारूढाय ते नमः ॥ ६८ ॥\n",
      "\n",
      "अविज्ञेयस्वरूपाय सुन्दराय नमो नमः ।\n",
      "उमाकान्त नमस्तेऽस्तु नमस्ते सर्वसाक्षिणे ॥ ६९ ॥\n",
      "\n",
      "हिरण्यबाहवे तुभ्यं हिरण्याभरणाय च ।\n",
      "नमो हिरण्यरूपाय रूपातीताय ते नमः ॥ ७० ॥\n",
      "\n",
      "हिरण्यपतये तुभ्यमम्बिकापतये नमः ।\n",
      "उमायाः पतये तुभ्यं नमः पापप्रणाशक ॥ ७१ ॥\n",
      "\n",
      "मीढुष्टमाय दुर्गाय कद्रुद्राय प्रचेतसे ।\n",
      "तव्यसे बिल्वपूज्याय नमः कल्याणरूपिणे ॥ ७२ ॥\n",
      "\n",
      "अपार कल्याण गुणार्णवाय\n",
      "श्री नीलकण्ठाय निरञ्जनाय ।\n",
      "कालान्तकायापि नमो नमस्ते\n",
      "दिक्कालरूपाय नमो नमस्ते ॥ ७३ ॥\n",
      "\n",
      "वेदान्तबृन्दस्तुत सद्गुणाय\n",
      "गुणप्रवीणाय गुणाश्रयाय ।\n",
      "श्री विश्वनाथाय नमो नमस्ते\n",
      "काशीनिवासाय नमो नमस्ते ॥ ७४ ॥\n",
      "\n",
      "अमेय सौन्दर्य सुधानिधान\n",
      "समृद्धिरूपाय नमो नमस्ते ।\n",
      "धराधराकार नमो नमस्ते\n",
      "धारास्वरूपाय नमो नमस्ते ॥ ७५ ॥\n",
      "\n",
      "नीहार शैलात्मज हृद्विहार\n",
      "प्रकाशहार प्रविभासि वीर ।\n",
      "वीरेश्वरापार दयानिधान\n",
      "पाहि प्रभो पाहि नमो नमस्ते ॥ ७६ ॥\n",
      "\n",
      "व्यास उवाच ।\n",
      "एवं स्तुत्वा महादेवं प्रणिपत्य पुनः पुनः ।\n",
      "कृताञ्जलिपुटस्तसौ पार्श्वे डुण्ठिविनायकः ॥ ७७ ॥\n",
      "\n",
      "तमालोक्य सुतं प्राप्तं वेदं वेदाङ्गपारगम् ।\n",
      "स्नेहाश्रुधारा संवीतं प्राह डुण्ठिं सदाशिवः ॥ ७८ ॥\n",
      "\n",
      "इति श्री शिवरहस्ये हराख्ये तृतीयांशे पूर्वार्थे गणेशकृत रुद्राध्याय स्तुतिः नाम दशमोऽध्यायः ।\n",
      "अनेन श्रीगणेशकृत श्लोकात्मक रुद्रध्याय पारायणेन श्री विश्वेश्वरः सुप्रीतः सुप्रसन्नो वरदो भवतु ।\n"
],
    "ta": [
      "த்⁴யாநம் ।\n",
      "ஆபாதால நப⁴꞉ ஸ்த²லாந்த பு⁴வந ப்³ரஹ்மாண்ட³மாவிஸ்பு²ர-\n",
      "-ஜ்ஜ்யோதி꞉ஸ்பா²டிகலிங்க³ மௌளிவிளஸத் பூர்ணேந்து³ வாந்தாம்ருதை꞉ ।\n",
      "அஸ்தோகாப்லுதமேகமீஶமநிஶம் ருத்³ராநுவாகாந் ஜபந்\n",
      "த்⁴யாயேதீ³ப்ஸிதஸித்³த⁴யே த்⁴ருவபத³ம் விப்ரோ(அ)பி⁴ஷிஞ்சேச்சி²வம் ॥\n",
      "\n",
      "ப்³ரஹ்மாண்ட³வ்யாப்ததே³ஹா ப⁴ஸித ஹிமருசா பா⁴ஸமாநா பு⁴ஜங்கை³꞉\n",
      "கண்டே² காலா꞉ கபர்தா³꞉ கலிதஶஶிகலாஶ்சண்ட³ கோத³ண்ட³ ஹஸ்தா꞉ ।\n",
      "த்ர்யக்ஷா ருத்³ராக்ஷமாலா꞉ ஸுலலிதவபுஷ꞉ ஶாம்ப⁴வா மூர்திபே⁴தா³꞉\n",
      "ருத்³ரா꞉ ஶ்ரீருத்³ரஸூக்த ப்ரகடித விப⁴வா꞉ ந꞉ ப்ரயச்ச²ந்து ஸௌக்²யம் ॥\n",
      "\n",
      "இத்யுக்த்வா ஸத்வரம் ஸாம்ப³ம் ஸ்ம்ருத்வா ஶங்கரபாது³கே ।\n",
      "த்⁴யாத்வா யயௌ க³ணாதீ⁴ஶ꞉ ஶிவஸந்நிதி⁴மாத³ராத் ॥\n",
      "\n",
      "தத꞉ ப்ரணம்ய ப³ஹுதா⁴ க்ருதாஞ்ஜலிபுட꞉ ப்ரபு⁴ம் ।\n",
      "ஶம்பு⁴ம் ஸ்தோதும் மதிம் சக்ரே ஸர்வாபீ⁴ஷ்டப்ரதா³யகம் ॥\n",
      "\n",
      "க³ணேஶ உவாச ।\n",
      "நமஸ்தே தே³வதே³வாய நமஸ்தே ருத்³ரமந்யவே ।\n",
      "நமஸ்தே சந்த்³ரசூடா³யாப்யுதோத இஷவே நம꞉ ॥ 1 ॥\n",
      "\n",
      "நமஸ்தே பார்வதீகாந்தாயைகரூபாய த⁴ந்வநே ।\n",
      "நமஸ்தே ப⁴க³வந் ஶம்போ⁴ பா³ஹுப்⁴யாமுத தே நம꞉ ॥ 2 ॥\n",
      "\n",
      "இஷு꞉ ஶிவதமா யா தே தயா ம்ருடா³ய ருத்³ர மாம் ।\n",
      "ஶிவம் த⁴நுர்யத்³ப³பூ⁴வ தேநாபி ம்ருட³யாது⁴நா ॥ 3 ॥\n",
      "\n",
      "ஶரவ்யா யா ஶிவதமா தயாபி ம்ருட³ய ப்ரபோ⁴ ।\n",
      "யா தே ருத்³ர ஶிவா நித்யம் ஸர்வமங்க³ளஸாத⁴நம் ॥ 4 ॥\n",
      "\n",
      "தயாபி⁴சாகஶீஹி த்வம் தநுவா மாமுமாபதே ।\n",
      "அகோ⁴ரயாபி தநுவா ருத்³ராத்³யா பாபகாஶிநீ ॥ 5 ॥\n",
      "\n",
      "யா தயா ம்ருட³ய ஸ்வாமிந் ஸதா³ ஶந்தமயா ப்ரபோ⁴ ।\n",
      "கி³ரிஶந்தம் மஹாருத்³ர ஹஸ்தே யாமிஷுமஸ்தவே ॥ 6 ॥\n",
      "\n",
      "பி³ப⁴ர்ஷி தாம் கி³ரித்ராத்³ய ஶிவாம் குரு ஶிவாபதே ।\n",
      "ஶிவேந வசஸா ருத்³ர நித்யம் வாசா வதா³மஸி ॥ 7 ॥\n",
      "\n",
      "த்வத்³ப⁴க்தி பரிபூதாங்க³ம் மஹிம்ஸீ꞉ புருஷம் ஜக³த் ।\n",
      "யச்ச ஶர்வ ஜக³த்ஸர்வமயக்ஷ்மம் ஸுமநா அஸத் ॥ 8 ॥\n",
      "\n",
      "யதா² ததா²வமாம் ருத்³ர தத³ந்யதா⁴பி மே ப்ரபோ⁴ ।\n",
      "ருத்³ர த்வம் ப்ரத²மோ தை³வ்யோ பி⁴ஷக் பாபவிநாஶக꞉ ॥ 9 ॥\n",
      "\n",
      "அதி⁴வக்தா(அ)த்⁴யவோசந்மாம் பா⁴வலிங்கா³ர்சகம் முதா³ ।\n",
      "அஹீந் ஸர்வாந் யாது தா⁴ந்ய꞉ ஸர்வா அப்யத்³ய ஜம்ப⁴யந் ॥ 10 ॥\n",
      "\n",
      "அஸௌ தாம்ரோருணோ ப³ப்⁴ரு꞉ நீலக்³ரீவ꞉ ஸுமங்க³ள꞉ ।\n",
      "விளோஹிதோஸ்த்வயம் ஶம்போ⁴ த்வத³தி⁴ஷ்டா²ந ஏவ ஹி ॥ 11 ॥\n",
      "\n",
      "நமோ நமஸ்தே ப⁴க³வந் நீலக்³ரீவாய மீடு⁴ஷே ।\n",
      "ஸஹஸ்ராக்ஷாய ஶுத்³தா⁴ய ஸச்சிதா³நந்த³மூர்தயே ॥ 12 ॥\n",
      "\n",
      "உப⁴யோகா³ர்த்நியோர்ஜ்யா யா த⁴ந்வநஸ்தாம் ப்ரமுஞ்சதாம் ।\n",
      "ஸம்ப்ராப்ய த⁴நுரந்யேஷாம் ப⁴யாய ப்ரப⁴விஷ்யதி ॥ 13 ॥\n",
      "\n",
      "அஸ்மத்³ப⁴ய விநாஶார்த² மது⁴நாப⁴யத³ ப்ரபோ⁴ ।\n",
      "யாஶ்ச தே ஹஸ்த இஷவ꞉ பரதா ப⁴க³வோ வாப ॥ 14 ॥\n",
      "\n",
      "அவதத்ய த⁴நுஶ்ச த்வம் ஸஹஸ்ராக்ஷ ஶதேஷுதே⁴ ।\n",
      "முகா² நிஶீர்ய ஶல்யாநாம் ஶிவோ ந꞉ ஸுமநா ப⁴வ ॥ 15 ॥\n",
      "\n",
      "விஜ்யம் த⁴நுரித³ம் பூ⁴யாத் விஶல்யோ பா³ணவாநபி ।\n",
      "அநேஶந்நிஷவஶ்சாபி ஹ்யாபு⁴ரஸ்து நிஷங்க³தி²꞉ ॥ 16 ॥\n",
      "\n",
      "கபர்தி³நோ மஹேஶஸ்ய யதி³ நாபு⁴ர்நிஷங்க³தி²꞉ ।\n",
      "இஷவோ பி ஸமர்தா²ஶ்சேத் ஸாமர்த்²யேது ப⁴யம் ப⁴வேத் ॥ 17 ॥\n",
      "\n",
      "யா தே ஹேதிர்த⁴நுர்ஹஸ்தே மீடு⁴ஷ்டம ப³பூ⁴வ யா ।\n",
      "தயா(அ)ஸ்மாந் விஶ்வதஸ்தேந பாலய த்வமயக்ஷ்மயா ॥ 18 ॥\n",
      "\n",
      "அநாததாயாயுதா⁴ய நமஸ்தே த்⁴ருஷ்ணவே நம꞉ ।\n",
      "பா³ஹுப்⁴யாம் த⁴ந்வநே ஶம்போ⁴ நமோ பூ⁴யோ நமோ நம꞉ ॥ 19 ॥\n",
      "\n",
      "பரிதே த⁴ந்வநோ ஹேதி꞉ விஶ்வதோ(அ)ஸ்மாந் வ்ருணக்து ந꞉ ।\n",
      "இஷுதி⁴ஸ்தவ யா தாவத³ஸ்மதா³ரே நிதே⁴ஹி தம் ॥ 20 ॥\n",
      "\n",
      "ஹிரண்யபா³ஹவே துப்⁴யம் ஸேநாந்யே தே நமோ நம꞉ ।\n",
      "தி³ஶாம் ச பதயே துப்⁴யம் பஶூநாம் பதயே நம꞉ ॥ 21 ॥\n",
      "\n",
      "த்விஷீமதே நமஸ்துப்⁴யம் நம꞉ ஸஸ்பிஞ்ஜராய தே ।\n",
      "நம꞉ பதீ²நாம் பதயே ப³ப்⁴லுஶாய நமோ நம꞉ ॥ 22 ॥\n",
      "\n",
      "நமோ விவ்யாதி⁴நேந்நாநாம் பதயே ப்ரப⁴வே நம꞉ ।\n",
      "நமஸ்தே ஹரிகேஶாய ருத்³ராயாஸ்தூபவீதிநே ॥ 23 ॥\n",
      "\n",
      "புஷ்டாநாம் பதயே துப்⁴யம் ஜக³தாம் பதயே நம꞉ ।\n",
      "ஸம்ஸார ஹேதி ரூபாய ருத்³ராயாப்யாததாயிநே ॥ 24 ॥\n",
      "\n",
      "க்ஷேத்ராணாம் பதயே துப்⁴யம் ஸூதாய ஸுக்ருதாத்மநே ।\n",
      "அஹந்த்யாய நமஸ்துப்⁴யம் வநாநாம் பதயே நம꞉ ॥ 25 ॥\n",
      "\n",
      "ரோஹிதாய ஸ்த²பதயே மந்த்ரிணே வாணிஜாய ச ।\n",
      "கக்ஷாணாம் பதயே துப்⁴யம் நமஸ்துப்⁴யம் பு⁴வந்தயே ॥ 26 ॥\n",
      "\n",
      "தத்³வாரிவஸ்க்ருதாயாஸ்து மஹாதே³வாய தே நம꞉ ।\n",
      "ஓஷாதீ⁴நாம் ச பதயே நமஸ்துப்⁴யம் மஹாத்மநே ॥ 27 ॥\n",
      "\n",
      "உச்சைர்கோ⁴ஷாய தீ⁴ராய தீ⁴ராந் க்ரந்த³யதே நம꞉ ॥ 28 ॥\n",
      "\n",
      "பத்தீநாம் பதயே துப்⁴யம் க்ருத்ஸ்நவீதாய தே நம꞉ ।\n",
      "தா⁴வதே த⁴வளாயாபி ஸத்த்வநாம் பதயே நம꞉ ॥ 29 ॥\n",
      "\n",
      "ஆவ்யாதி⁴நீநாம் பதயே ககுபா⁴ய நிஷங்கி³ணே ।\n",
      "ஸ்தேநாநாம் பதயே துப்⁴யம் தி³வ்யேஷுதி⁴மதே நம꞉ ॥ 30 ॥\n",
      "\n",
      "தஸ்கராணாம் ச பதயே வஞ்சதே பரிவஞ்சதே ।\n",
      "ஸ்தாயூநாம் பதயே துப்⁴யம் நமஸ்தே(அ)ஸ்து நிசேரவே ॥ 31 ॥\n",
      "\n",
      "நம꞉ பரிசராயா(அ)பி மஹாருத்³ராய தே நம꞉ ।\n",
      "அரண்யாநாம் ச பதயே முஷ்ணதாம் பதயே நம꞉ ॥ 32 ॥\n",
      "\n",
      "உஷ்ணீஷிணே நமஸ்துப்⁴யம் நமோ கி³ரிசராய தே ।\n",
      "குலுஞ்சாநாம் ச பதயே நமஸ்துப்⁴யம் ப⁴வாய ச ॥ 33 ॥\n",
      "\n",
      "நமோ ருத்³ராய ஶர்வாய துப்⁴யம் பஶுபதே நம꞉ ।\n",
      "நம உக்³ராய பீ⁴மாய நமஶ்சாக்³ரேவதா⁴ய ச ॥ 34 ॥\n",
      "\n",
      "நமோ தூ³ரேவதா⁴யா(அ)பி நமோ ஹந்த்ரே நமோ நம꞉ ।\n",
      "ஹநீயஸே நமஸ்துப்⁴யம் நீலக்³ரீவாய தே நம꞉ ॥ 35 ॥\n",
      "\n",
      "நமஸ்தே ஶிதிகண்டா²ய நமஸ்தே(அ)ஸ்து கபர்தி³நே ।\n",
      "நமஸ்தே வ்யுப்தகேஶாய ஸஹஸ்ராக்ஷாய மீடு⁴ஷே ॥ 36 ॥\n",
      "\n",
      "கி³ரிஶாய நமஸ்தே(அ)ஸ்து ஶிபிவிஷ்டாய தே நம꞉ ।\n",
      "நமஸ்தே ஶம்ப⁴வே துப்⁴யம் மயோப⁴வ நமோ(அ)ஸ்து தே ॥ 37 ॥\n",
      "\n",
      "மயஸ்கர நமஸ்துப்⁴யம் ஶங்கராய நமோ நம꞉ ।\n",
      "நம꞉ ஶிவாய ஶர்வாய நம꞉ ஶிவதராய ச ॥ 38 ॥\n",
      "\n",
      "நமஸ்தீர்த்²யாய கூல்யாய நம꞉ பார்யாய தே நம꞉ ।\n",
      "ஆவார்யாய நமஸ்தே(அ)ஸ்து நம꞉ ப்ரதரணாய ச ॥ 39 ॥\n",
      "\n",
      "நம உத்தரணாயா(அ)பி ஹராதார்யாய தே நம꞉ ।\n",
      "ஆலாத்³யாய நமஸ்தே(அ)ஸ்து ப⁴க்தாநாம் வரதா³ய ச ॥ 40 ॥\n",
      "\n",
      "நம꞉ ஶஷ்ப்யாய பே²ந்யாய ஸிகத்யாய நமோ நம꞉ ।\n",
      "ப்ரவாஹ்யாய நமஸ்தே(அ)ஸ்து ஹ்ரஸ்வாயா(அ)ஸ்து நமோ நம꞉ ॥ 41 ॥\n",
      "\n",
      "வாமநாய நமஸ்தே(அ)ஸ்து ப்³ருஹதே ச நமோ நம꞉ ।\n",
      "வர்ஷீயஸே நமஸ்தே(அ)ஸ்து நமோ வ்ருத்³தா⁴ய தே நம꞉ ॥ 42 ॥\n",
      "\n",
      "ஸம்வ்ருத்⁴வநே நமஸ்துப்⁴யமக்³ரியாய நமோ நம꞉ ।\n",
      "ப்ரத²மாய நமஸ்துப்⁴யமாஶவே சாஜிராய ச ॥ 43 ॥\n",
      "\n",
      "ஶீக்⁴ரியாய நமஸ்தே(அ)ஸ்து ஶீப்⁴யாய ச நமோ நம꞉ ।\n",
      "நம ஊர்ம்யாய ஶர்வாயா(அ)ப்யவஸ்வந்யாய தே நம꞉ ॥ 44 ॥\n",
      "\n",
      "ஸ்ரோதஸ்யாய நமஸ்துப்⁴யம் த்³வீப்யாய ச நமோ நம꞉ ।\n",
      "ஜ்யேஷ்டா²ய ச நமஸ்துப்⁴யம் கநிஷ்டா²ய நமோ நம꞉ ॥ 45 ॥\n",
      "\n",
      "பூர்வஜாய நமஸ்துப்⁴யம் நமோஸ்த்வபரஜாய ச ।\n",
      "மத்⁴யமாய நமஸ்துப்⁴யமபக³ள்பா⁴ய தே நம꞉ ॥ 46 ॥\n",
      "\n",
      "ஜக⁴ந்யாய நமஸ்துப்⁴யம் பு³த்⁴நியாய நமோ நம꞉ ।\n",
      "ஸோப்⁴யாய ப்ரதிஸர்யாய யாம்யாய ச நமோ நம꞉ ॥ 47 ॥\n",
      "\n",
      "க்ஷேம்யாய ச நமஸ்துப்⁴யம் யாம்யாய ச நமோ நம꞉ ।\n",
      "உர்வர்யாய நமஸ்துப்⁴யம் க²ல்யாய ச நமோ நம꞉ ॥ 48 ॥\n",
      "\n",
      "ஶ்லோக்யாய சாவஸாந்யாயாவஸ்வந்யாய ச தே நம꞉ ।\n",
      "நமோ வந்யாய கக்ஷ்யாய மௌஞ்ஜ்யாய ச நமோ நம꞉ ॥ 49 ॥\n",
      "\n",
      "ஶ்ரவாய ச நமஸ்துப்⁴யம் ப்ரதிஶ்ரவ நமோ நம꞉ ।\n",
      "ஆஶுஷேணாய ஶூராய நமோஸ்த்வா(அ)ஶுரதா²ய ச ॥ 50 ॥\n",
      "\n",
      "வரூதி²நே பர்மிணே ச பி³ல்மிநே ச நமோ நம꞉ ।\n",
      "ஶ்ருதாய ஶ்ருதஸேநாய நம꞉ கவசிநே நம꞉ ॥ 51 ॥\n",
      "\n",
      "து³ந்து³ப்⁴யாய நமஸ்துப்⁴யமாஹநந்யாய தே நம꞉ ।\n",
      "ப்ரஹிதாய நமஸ்துப்⁴யம் த்⁴ருஷ்ணவே ப்ரம்ருஶாய ச ॥ 52 ॥\n",
      "\n",
      "பாராய பாரவிந்தா³ய நமஸ்தீக்ஷ்ணேஷவே நம꞉ ।\n",
      "ஸுத⁴ந்வநே நமஸ்துப்⁴யம் ஸ்வாயுதா⁴ய நமோ நம꞉ ॥ 53 ॥\n",
      "\n",
      "நம꞉ ஸ்ருத்யாய பத்²யாய நம꞉ காட்யாய தே நம꞉ ।\n",
      "நமோ நீப்யாய ஸூத்³யாய ஸரஸ்யாய ச தே நம꞉ ॥ 54 ॥\n",
      "\n",
      "நமோ நாத்³யாய ப⁴வ்யாய வைஶந்தாய நமோ நம꞉ ।\n",
      "அவட்யாய நமஸ்துப்⁴யம் நம꞉ கூப்யாய தே நம꞉ ॥ 55 ॥\n",
      "\n",
      "அவர்ஷ்யாய ச வர்ஷ்யாய மேக்⁴யாய ச நமோ நம꞉ ।\n",
      "வித்³யுத்யாய நமஸ்துப்⁴யமீத்⁴ரியாய நமோ நம꞉ ॥ 56 ॥\n",
      "\n",
      "ஆதப்யாய நமஸ்துப்⁴யம் வாத்யாய ச நமோ நம꞉ ।\n",
      "ரேஷ்மியாய நமஸ்துப்⁴யம் வாஸ்தவ்யாய ச தே நம꞉ ॥ 57 ॥\n",
      "\n",
      "வாஸ்துபாய நமஸ்துப்⁴யம் நம꞉ ஸோமாய தே நம꞉ ।\n",
      "நமோ ருத்³ராய தாம்ராயா(அ)ப்யருணாய ச தே நம꞉ ॥ 58 ॥\n",
      "\n",
      "நம உக்³ராய பீ⁴மாய நம꞉ ஶங்கா³ய தே நம꞉ ।\n",
      "நமஸ்தீர்த்²யாய கூல்யாய ஸிகத்யாய நமோ நம꞉ ॥ 59 ॥\n",
      "\n",
      "ப்ரவாஹ்யாய நமஸ்துப்⁴யமிரிண்யாய நமோ நம꞉ ।\n",
      "நமஸ்தே சந்த்³ரசூடா³ய ப்ரபத்²யாய நமோ நம꞉ ॥ 60 ॥\n",
      "\n",
      "கிம்ஶிலாய நமஸ்தே(அ)ஸ்து க்ஷயணாய ச தே நம꞉ ।\n",
      "கபர்தி³நே நமஸ்தே(அ)ஸ்து நமஸ்தே(அ)ஸ்து புலஸ்தயே ॥ 61 ॥\n",
      "\n",
      "நமோ கோ³ஷ்ட்²யாய க்³ருஹ்யாய க்³ரஹாணாம் பதயே நம꞉ ।\n",
      "நமஸ்தல்ப்யாய கே³ஹ்யாய கு³ஹாவாஸாய தே நம꞉ ॥ 62 ॥\n",
      "\n",
      "காட்யாய க³ஹ்வரேஷ்டா²ய ஹ்ரத³ய்யாய ச தே நம꞉ ।\n",
      "நிவேஷ்ப்யாய நமஸ்துப்⁴யம் பாம்ஸவ்யாய தே நம꞉ ॥ 63 ॥\n",
      "\n",
      "ரஜஸ்யாய நமஸ்துப்⁴யம் பராத்பர தராய ச ।\n",
      "நமஸ்தே ஹரிகேஶாய ஶுஷ்க்யாய ச நமோ நம꞉ ॥ 64 ॥\n",
      "\n",
      "ஹரித்யாய நமஸ்துப்⁴யம் ஹரித்³வர்ணாய தே நம꞉ ।\n",
      "நம꞉ உர்ம்யாய ஸூர்ம்யாய பர்ண்யாய ச நமோ நம꞉ ॥ 65 ॥\n",
      "\n",
      "நமோபகு³ரமாணாய பர்ணஶத்³யாய தே நம꞉ ।\n",
      "அபி⁴க்⁴நதே சாக்²கி²த³தே நம꞉ ப்ரக்²கி²த³தே நம꞉ ॥ 66 ॥\n",
      "\n",
      "விஶ்வரூபாய விஶ்வாய விஶ்வாதா⁴ராய தே நம꞉ ।\n",
      "த்ர்யம்ப³காய ச ருத்³ராய கி³ரிஜாபதயே நம꞉ ॥ 67 ॥\n",
      "\n",
      "மணிகோடீரகோடிஸ்த² காந்திதீ³ப்தாய தே நம꞉ ।\n",
      "வேத³வேதா³ந்த வேத்³யாய வ்ருஷாரூடா⁴ய தே நம꞉ ॥ 68 ॥\n",
      "\n",
      "அவிஜ்ஞேயஸ்வரூபாய ஸுந்த³ராய நமோ நம꞉ ।\n",
      "உமாகாந்த நமஸ்தே(அ)ஸ்து நமஸ்தே ஸர்வஸாக்ஷிணே ॥ 69 ॥\n",
      "\n",
      "ஹிரண்யபா³ஹவே துப்⁴யம் ஹிரண்யாப⁴ரணாய ச ।\n",
      "நமோ ஹிரண்யரூபாய ரூபாதீதாய தே நம꞉ ॥ 70 ॥\n",
      "\n",
      "ஹிரண்யபதயே துப்⁴யமம்பி³காபதயே நம꞉ ।\n",
      "உமாயா꞉ பதயே துப்⁴யம் நம꞉ பாபப்ரணாஶக ॥ 71 ॥\n",
      "\n",
      "மீடு⁴ஷ்டமாய து³ர்கா³ய கத்³ருத்³ராய ப்ரசேதஸே ।\n",
      "தவ்யஸே பி³ல்வபூஜ்யாய நம꞉ கல்யாணரூபிணே ॥ 72 ॥\n",
      "\n",
      "அபார கல்யாண கு³ணார்ணவாய\n",
      "ஶ்ரீ நீலகண்டா²ய நிரஞ்ஜநாய ।\n",
      "காலாந்தகாயாபி நமோ நமஸ்தே\n",
      "தி³க்காலரூபாய நமோ நமஸ்தே ॥ 73 ॥\n",
      "\n",
      "வேதா³ந்தப்³ருந்த³ஸ்துத ஸத்³கு³ணாய\n",
      "கு³ணப்ரவீணாய கு³ணாஶ்ரயாய ।\n",
      "ஶ்ரீ விஶ்வநாதா²ய நமோ நமஸ்தே\n",
      "காஶீநிவாஸாய நமோ நமஸ்தே ॥ 74 ॥\n",
      "\n",
      "அமேய ஸௌந்த³ர்ய ஸுதா⁴நிதா⁴ந\n",
      "ஸம்ருத்³தி⁴ரூபாய நமோ நமஸ்தே ।\n",
      "த⁴ராத⁴ராகார நமோ நமஸ்தே\n",
      "தா⁴ராஸ்வரூபாய நமோ நமஸ்தே ॥ 75 ॥\n",
      "\n",
      "நீஹார ஶைலாத்மஜ ஹ்ருத்³விஹார\n",
      "ப்ரகாஶஹார ப்ரவிபா⁴ஸி வீர ।\n",
      "வீரேஶ்வராபார த³யாநிதா⁴ந\n",
      "பாஹி ப்ரபோ⁴ பாஹி நமோ நமஸ்தே ॥ 76 ॥\n",
      "\n",
      "வ்யாஸ உவாச ।\n",
      "ஏவம் ஸ்துத்வா மஹாதே³வம் ப்ரணிபத்ய புந꞉ புந꞉ ।\n",
      "க்ருதாஞ்ஜலிபுடஸ்தஸ்தௌ² பார்ஶ்வே டு³ண்டி²விநாயக꞉ ॥ 77 ॥\n",
      "\n",
      "தமாலோக்ய ஸுதம் ப்ராப்தம் வேத³ம் வேதா³ங்க³பாரக³ம் ।\n",
      "ஸ்நேஹாஶ்ருதா⁴ரா ஸம்வீதம் ப்ராஹ டு³ண்டி²ம் ஸதா³ஶிவ꞉ ॥ 78 ॥\n",
      "\n",
      "இதி ஶ்ரீ ஶிவரஹஸ்யே ஹராக்²யே த்ருதீயாம்ஶே பூர்வார்தே² க³ணேஶக்ருத ருத்³ராத்⁴யாய ஸ்துதி꞉ நாம த³ஶமோ(அ)த்⁴யாய꞉ ।\n",
      "அநேந ஶ்ரீக³ணேஶக்ருத ஶ்லோகாத்மக ருத்³ரத்⁴யாய பாராயணேந ஶ்ரீ விஶ்வேஶ்வர꞉ ஸுப்ரீத꞉ ஸுப்ரஸந்நோ வரதோ³ ப⁴வது ।\n"
]
  },
  "mangalam": {
    "te": "మంగళం మహత్",
    "en": "Maṅgalaṃ Mahat",
    "hi": "मंगलं महत्",
    "ta": "மங்களம் மஹத்"
  }
}
